{"date":"2022-03-20","stores":{"하남":[{"item":"I 아메리카노(E)","qty":12,"net":51600,"cat_big":"매장메뉴","cat_mid":"음료","cat_small":"커피"},{"item":"카페라떼","qty":8,"net":38400,"cat_big":"매장메뉴","cat_mid":"음료","cat_small":"커피"},{"item":"바닐라 라떼","qty":1,"net":5000,"cat_big":"매장메뉴","cat_mid":"음료","cat_small":"커피"},{"item":"연유 라떼","qty":2,"net":11000,"cat_big":"매장메뉴","cat_mid":"음료","cat_small":"커피"},{"item":"콜드브루 RTD(타이거즈)","qty":1,"net":5500,"cat_big":"매장메뉴","cat_mid":"음료","cat_small":"커피"},{"item":"콜드브루 라떼","qty":2,"net":11000,"cat_big":"매장메뉴","cat_mid":"음료","cat_small":"커피"},{"item":"라떼 플롯","qty":3,"net":19500,"cat_big":"매장메뉴","cat_mid":"음료","cat_small":"커피"},{"item":"아메리카노(B)","qty":11,"net":47300,"cat_big":"매장메뉴","cat_mid":"음료","cat_small":"커피"},{"item":"I 아메리카노(B)","qty":21,"net":90300,"cat_big":"매장메뉴","cat_mid":"음료","cat_small":"커피"},{"item":"아메리카노(E)","qty":4,"net":17200,"cat_big":"매장메뉴","cat_mid":"음료","cat_small":"커피"},{"item":"플랫화이트","qty":3,"net":14400,"cat_big":"매장메뉴","cat_mid":"음료","cat_small":"커피"},{"item":"I 플랫화이트","qty":2,"net":9600,"cat_big":"매장메뉴","cat_mid":"음료","cat_small":"커피"},{"item":"I 연유 라떼","qty":3,"net":16500,"cat_big":"매장메뉴","cat_mid":"음료","cat_small":"커피"},{"item":"I 카라멜 마끼아또","qty":1,"net":5500,"cat_big":"매장메뉴","cat_mid":"음료","cat_small":"커피"},{"item":"I 바닐라라떼","qty":4,"net":20000,"cat_big":"매장메뉴","cat_mid":"음료","cat_small":"커피"},{"item":"I 카페라떼","qty":7,"net":33600,"cat_big":"매장메뉴","cat_mid":"음료","cat_small":"커피"},{"item":"I 이디오피아 구지","qty":2,"net":10000,"cat_big":"매장메뉴","cat_mid":"음료","cat_small":"Drip"},{"item":"I콜롬비아 디카페인","qty":1,"net":6000,"cat_big":"매장메뉴","cat_mid":"음료","cat_small":"Drip"},{"item":"산타로사 토피","qty":1,"net":7000,"cat_big":"매장메뉴","cat_mid":"음료","cat_small":"Drip"},{"item":"I산타로사 토피","qty":1,"net":7000,"cat_big":"매장메뉴","cat_mid":"음료","cat_small":"Drip"},{"item":"인크 슈페너","qty":4,"net":24000,"cat_big":"매장메뉴","cat_mid":"음료","cat_small":"시그니처"},{"item":"인크 아포가토","qty":4,"net":28000,"cat_big":"매장메뉴","cat_mid":"음료","cat_small":"시그니처"},{"item":"자카파 밀크","qty":2,"net":15000,"cat_big":"매장메뉴","cat_mid":"음료","cat_small":"시그니처"},{"item":"메도우","qty":2,"net":10000,"cat_big":"매장메뉴","cat_mid":"음료","cat_small":"TEA"},{"item":"페퍼민트 리브스","qty":2,"net":10000,"cat_big":"매장메뉴","cat_mid":"음료","cat_small":"TEA"},{"item":"I 로드 버가모트","qty":1,"net":5000,"cat_big":"매장메뉴","cat_mid":"음료","cat_small":"TEA"},{"item":"차이 밀크 라떼","qty":4,"net":22000,"cat_big":"매장메뉴","cat_mid":"음료","cat_small":"NON 커피"},{"item":"시트러스 주스","qty":3,"net":19500,"cat_big":"매장메뉴","cat_mid":"음료","cat_small":"에이드/주스/블렌디드"},{"item":"청포도라임에이드","qty":3,"net":18000,"cat_big":"매장메뉴","cat_mid":"음료","cat_small":"에이드/주스/블렌디드"},{"item":"인크선셋에이드","qty":2,"net":13000,"cat_big":"매장메뉴","cat_mid":"음료","cat_small":"에이드/주스/블렌디드"},{"item":"민트초코칩 블렌디드","qty":1,"net":6000,"cat_big":"매장메뉴","cat_mid":"음료","cat_small":"에이드/주스/블렌디드"},{"item":"우리 쑥 블렌디드","qty":1,"net":6000,"cat_big":"매장메뉴","cat_mid":"음료","cat_small":"에이드/주스/블렌디드"},{"item":"딸기요거트","qty":2,"net":14400,"cat_big":"매장메뉴","cat_mid":"음료","cat_small":"시즌음료"},{"item":"인크메리베리","qty":1,"net":7300,"cat_big":"매장메뉴","cat_mid":"음료","cat_small":"시즌음료"},{"item":"러블리레몬에이드","qty":1,"net":7000,"cat_big":"매장메뉴","cat_mid":"음료","cat_small":"시즌음료"},{"item":"밀크 아이스크림","qty":1,"net":3800,"cat_big":"매장메뉴","cat_mid":"음료","cat_small":"아이스크림"},{"item":"밤식빵","qty":3,"net":13500,"cat_big":"매장메뉴","cat_mid":"베이커리","cat_small":"브레드"},{"item":"찹쌀 브리오슈 식빵","qty":2,"net":9000,"cat_big":"매장메뉴","cat_mid":"베이커리","cat_small":"브레드"},{"item":"단팥빵","qty":2,"net":5000,"cat_big":"매장메뉴","cat_mid":"베이커리","cat_small":"브레드"},{"item":"소보로","qty":3,"net":6600,"cat_big":"매장메뉴","cat_mid":"베이커리","cat_small":"브레드"},{"item":"흑임자 소보로","qty":3,"net":9000,"cat_big":"매장메뉴","cat_mid":"베이커리","cat_small":"브레드"},{"item":"어니언 크림치즈","qty":2,"net":9000,"cat_big":"매장메뉴","cat_mid":"베이커리","cat_small":"브레드"},{"item":"시오빵","qty":8,"net":20000,"cat_big":"매장메뉴","cat_mid":"베이커리","cat_small":"브레드"},{"item":"리얼초코초코","qty":3,"net":9900,"cat_big":"매장메뉴","cat_mid":"베이커리","cat_small":"브레드"},{"item":"블랙트리플","qty":1,"net":4500,"cat_big":"매장메뉴","cat_mid":"베이커리","cat_small":"브레드"},{"item":"앙버터 바게트","qty":4,"net":18000,"cat_big":"매장메뉴","cat_mid":"베이커리","cat_small":"브레드"},{"item":"갈릭바게트","qty":1,"net":4000,"cat_big":"매장메뉴","cat_mid":"베이커리","cat_small":"브레드"},{"item":"고르곤 치즈 바게트","qty":2,"net":9600,"cat_big":"매장메뉴","cat_mid":"베이커리","cat_small":"브레드"},{"item":"먹물 롤치즈 치아바타","qty":3,"net":10500,"cat_big":"매장메뉴","cat_mid":"베이커리","cat_small":"브레드"},{"item":"베이컨치즈올리브 치아바타","qty":2,"net":7600,"cat_big":"매장메뉴","cat_mid":"베이커리","cat_small":"브레드"},{"item":"모카번","qty":3,"net":10500,"cat_big":"매장메뉴","cat_mid":"베이커리","cat_small":"브레드"},{"item":"베이컨롤","qty":2,"net":8000,"cat_big":"매장메뉴","cat_mid":"베이커리","cat_small":"브레드"},{"item":"크로크무슈","qty":1,"net":4000,"cat_big":"매장메뉴","cat_mid":"베이커리","cat_small":"브레드"},{"item":"마스카포네 크로와상","qty":3,"net":12600,"cat_big":"매장메뉴","cat_mid":"베이커리","cat_small":"페스츄리"},{"item":"몽블랑(판매중단)","qty":1,"net":5500,"cat_big":"매장메뉴","cat_mid":"베이커리","cat_small":"페스츄리"},{"item":"레몬크런치","qty":1,"net":5500,"cat_big":"매장메뉴","cat_mid":"베이커리","cat_small":"페스츄리"},{"item":"라즈베리크런치","qty":2,"net":11000,"cat_big":"매장메뉴","cat_mid":"베이커리","cat_small":"페스츄리"},{"item":"쿠키앤크림 케이크","qty":2,"net":13200,"cat_big":"매장메뉴","cat_mid":"베이커리","cat_small":"케이크"},{"item":"딸기듬뿍 케이크박스","qty":2,"net":14800,"cat_big":"매장메뉴","cat_mid":"베이커리","cat_small":"케이크"},{"item":"당근 케이크박스","qty":1,"net":6000,"cat_big":"매장메뉴","cat_mid":"베이커리","cat_small":"케이크"},{"item":"레몬 파운드","qty":2,"net":7000,"cat_big":"매장메뉴","cat_mid":"베이커리","cat_small":"구움과자"},{"item":"바닐라 마들렌","qty":5,"net":14000,"cat_big":"매장메뉴","cat_mid":"베이커리","cat_small":"구움과자"},{"item":"플레인 휘낭시에","qty":2,"net":6000,"cat_big":"매장메뉴","cat_mid":"베이커리","cat_small":"구움과자"},{"item":"소금초코 휘낭시에","qty":2,"net":7000,"cat_big":"매장메뉴","cat_mid":"베이커리","cat_small":"구움과자"},{"item":"레몬 마들렌","qty":2,"net":6000,"cat_big":"매장메뉴","cat_mid":"베이커리","cat_small":"구움과자"},{"item":"쇼콜라 프로겐트","qty":2,"net":9000,"cat_big":"매장메뉴","cat_mid":"베이커리","cat_small":"구움과자"},{"item":"카카오 버터쿠키","qty":1,"net":4900,"cat_big":"매장메뉴","cat_mid":"베이커리","cat_small":"구움과자"},{"item":"미니 플레인 스콘","qty":3,"net":10800,"cat_big":"매장메뉴","cat_mid":"베이커리","cat_small":"구움과자"},{"item":"인크 베이직 블랜드 200g","qty":1,"net":11000,"cat_big":"매장메뉴","cat_mid":"MD","cat_small":"커피류"},{"item":"콜롬비아 그란데 버번 200g","qty":1,"net":13000,"cat_big":"매장메뉴","cat_mid":"MD","cat_small":"커피류"},{"item":"인크포스터달력","qty":2,"net":2000,"cat_big":"매장메뉴","cat_mid":"MD","cat_small":"기타"},{"item":"크라프트 쇼핑백","qty":1,"net":200,"cat_big":"매장메뉴","cat_mid":"MD","cat_small":"포장"},{"item":"포장비","qty":1,"net":100,"cat_big":"매장메뉴","cat_mid":"MD","cat_small":"포장"},{"item":"바닐라라떼","qty":1,"net":5000,"cat_big":"매장메뉴","cat_mid":"스마트오더","cat_small":"스마트오더_커피"}],"가산":[{"item":"샷추가","qty":2,"net":2000,"cat_big":"가산점","cat_mid":"가산점","cat_small":"COFFEE"},{"item":"--------------","qty":260,"net":0,"cat_big":"가산점","cat_mid":"가산점","cat_small":"속성메뉴"},{"item":"텀블러","qty":3,"net":0,"cat_big":"가산점","cat_mid":"가산점","cat_small":"속성메뉴"},{"item":"얼음 많이","qty":2,"net":0,"cat_big":"가산점","cat_mid":"가산점","cat_small":"속성메뉴"},{"item":"덜 달게","qty":1,"net":0,"cat_big":"가산점","cat_mid":"가산점","cat_small":"속성메뉴"},{"item":"베이커리 포장","qty":6,"net":0,"cat_big":"가산점","cat_mid":"가산점","cat_small":"BAKERY"},{"item":"베이커리 드시고","qty":225,"net":0,"cat_big":"가산점","cat_mid":"가산점","cat_small":"ETC"},{"item":"베이커리 픽업ㅇ","qty":107,"net":0,"cat_big":"가산점","cat_mid":"가산점","cat_small":"ETC"},{"item":"I 아메리카노(E)","qty":224,"net":963200,"cat_big":"매장메뉴","cat_mid":"음료","cat_small":"커피"},{"item":"카페라떼","qty":27,"net":129600,"cat_big":"매장메뉴","cat_mid":"음료","cat_small":"커피"},{"item":"바닐라 라떼","qty":15,"net":75000,"cat_big":"매장메뉴","cat_mid":"음료","cat_small":"커피"},{"item":"카페모카","qty":1,"net":5500,"cat_big":"매장메뉴","cat_mid":"음료","cat_small":"커피"},{"item":"카라멜 마끼아또","qty":1,"net":5500,"cat_big":"매장메뉴","cat_mid":"음료","cat_small":"커피"},{"item":"연유 라떼","qty":3,"net":16500,"cat_big":"매장메뉴","cat_mid":"음료","cat_small":"커피"},{"item":"콜드브루 라떼","qty":3,"net":16500,"cat_big":"매장메뉴","cat_mid":"음료","cat_small":"커피"},{"item":"그린티에쏘 라떼","qty":2,"net":11000,"cat_big":"매장메뉴","cat_mid":"음료","cat_small":"커피"},{"item":"아메리카노(E)","qty":71,"net":305300,"cat_big":"매장메뉴","cat_mid":"음료","cat_small":"커피"},{"item":"에스프레소(E)","qty":3,"net":12900,"cat_big":"매장메뉴","cat_mid":"음료","cat_small":"커피"},{"item":"플랫화이트","qty":9,"net":43200,"cat_big":"매장메뉴","cat_mid":"음료","cat_small":"커피"},{"item":"I 플랫화이트","qty":5,"net":24000,"cat_big":"매장메뉴","cat_mid":"음료","cat_small":"커피"},{"item":"I 연유 라떼","qty":16,"net":88000,"cat_big":"매장메뉴","cat_mid":"음료","cat_small":"커피"},{"item":"I 카라멜 마끼아또","qty":4,"net":22000,"cat_big":"매장메뉴","cat_mid":"음료","cat_small":"커피"},{"item":"I 카페모카","qty":7,"net":38500,"cat_big":"매장메뉴","cat_mid":"음료","cat_small":"커피"},{"item":"I 바닐라라떼","qty":26,"net":130000,"cat_big":"매장메뉴","cat_mid":"음료","cat_small":"커피"},{"item":"I 카페라떼","qty":47,"net":225600,"cat_big":"매장메뉴","cat_mid":"음료","cat_small":"커피"},{"item":"[행사]아메리카노","qty":6,"net":0,"cat_big":"매장메뉴","cat_mid":"음료","cat_small":"커피"},{"item":"[행사]ICE 아메리카노","qty":6,"net":0,"cat_big":"매장메뉴","cat_mid":"음료","cat_small":"커피"},{"item":"I 아메리카노","qty":10,"net":45000,"cat_big":"매장메뉴","cat_mid":"음료","cat_small":"커피"},{"item":"I 크림 커피","qty":1,"net":5500,"cat_big":"매장메뉴","cat_mid":"음료","cat_small":"커피"},{"item":"NEW콜드브루RTD","qty":8,"net":44000,"cat_big":"매장메뉴","cat_mid":"음료","cat_small":"커피"},{"item":"이디오피아 단세모모라","qty":2,"net":10000,"cat_big":"매장메뉴","cat_mid":"음료","cat_small":"Drip"},{"item":"이디오피아 구지","qty":3,"net":15000,"cat_big":"매장메뉴","cat_mid":"음료","cat_small":"Drip"},{"item":"I 이디오피아 단세모모라","qty":5,"net":25000,"cat_big":"매장메뉴","cat_mid":"음료","cat_small":"Drip"},{"item":"I 이디오피아 구지","qty":1,"net":5000,"cat_big":"매장메뉴","cat_mid":"음료","cat_small":"Drip"},{"item":"콜롬비아 디카페인","qty":2,"net":12000,"cat_big":"매장메뉴","cat_mid":"음료","cat_small":"Drip"},{"item":"I콜롬비아 디카페인","qty":12,"net":72000,"cat_big":"매장메뉴","cat_mid":"음료","cat_small":"Drip"},{"item":"콜롬비아 토피","qty":1,"net":7000,"cat_big":"매장메뉴","cat_mid":"음료","cat_small":"Drip"},{"item":"I 콜롬비아 IPA","qty":2,"net":14000,"cat_big":"매장메뉴","cat_mid":"음료","cat_small":"Drip"},{"item":"I 콜롬비아 토피","qty":2,"net":14000,"cat_big":"매장메뉴","cat_mid":"음료","cat_small":"Drip"},{"item":"콜롬비아 버본","qty":6,"net":30000,"cat_big":"매장메뉴","cat_mid":"음료","cat_small":"Drip"},{"item":"i 콜롬비아 버본","qty":8,"net":40000,"cat_big":"매장메뉴","cat_mid":"음료","cat_small":"Drip"},{"item":"케냐 피베리","qty":5,"net":27500,"cat_big":"매장메뉴","cat_mid":"음료","cat_small":"Drip"},{"item":"I 케냐 피베리 필터","qty":2,"net":11000,"cat_big":"매장메뉴","cat_mid":"음료","cat_small":"Drip"},{"item":"인크 슈페너","qty":34,"net":204000,"cat_big":"매장메뉴","cat_mid":"음료","cat_small":"시그니처"},{"item":"인크 아포가토","qty":9,"net":63000,"cat_big":"매장메뉴","cat_mid":"음료","cat_small":"시그니처"},{"item":"자카파 밀크","qty":25,"net":187500,"cat_big":"매장메뉴","cat_mid":"음료","cat_small":"시그니처"},{"item":"자스민 실버 팁","qty":3,"net":16500,"cat_big":"매장메뉴","cat_mid":"음료","cat_small":"TEA"},{"item":"로즈시티 겐마이차","qty":1,"net":5500,"cat_big":"매장메뉴","cat_mid":"음료","cat_small":"TEA"},{"item":"메도우","qty":6,"net":30000,"cat_big":"매장메뉴","cat_mid":"음료","cat_small":"TEA"},{"item":"페퍼민트 리브스","qty":2,"net":10000,"cat_big":"매장메뉴","cat_mid":"음료","cat_small":"TEA"},{"item":"로드 버가모트","qty":2,"net":10000,"cat_big":"매장메뉴","cat_mid":"음료","cat_small":"TEA"},{"item":"포틀랜드 블랙퍼스트","qty":2,"net":10000,"cat_big":"매장메뉴","cat_mid":"음료","cat_small":"TEA"},{"item":"I 메도우","qty":2,"net":10000,"cat_big":"매장메뉴","cat_mid":"음료","cat_small":"TEA"},{"item":"I 페퍼민트 리브스","qty":2,"net":10000,"cat_big":"매장메뉴","cat_mid":"음료","cat_small":"TEA"},{"item":"I 로드 버가모트","qty":1,"net":5000,"cat_big":"매장메뉴","cat_mid":"음료","cat_small":"TEA"},{"item":"I 포틀랜드 블랙퍼스트","qty":1,"net":5000,"cat_big":"매장메뉴","cat_mid":"음료","cat_small":"TEA"},{"item":"녹차 라떼","qty":3,"net":16500,"cat_big":"매장메뉴","cat_mid":"음료","cat_small":"NON 커피"},{"item":"카카오 라떼","qty":3,"net":16500,"cat_big":"매장메뉴","cat_mid":"음료","cat_small":"NON 커피"},{"item":"차이 밀크 라떼","qty":2,"net":11000,"cat_big":"매장메뉴","cat_mid":"음료","cat_small":"NON 커피"},{"item":"I 녹차라떼","qty":6,"net":33000,"cat_big":"매장메뉴","cat_mid":"음료","cat_small":"NON 커피"},{"item":"I 카카오 라떼","qty":2,"net":11000,"cat_big":"매장메뉴","cat_mid":"음료","cat_small":"NON 커피"},{"item":"I 차이 밀크 라떼","qty":6,"net":33000,"cat_big":"매장메뉴","cat_mid":"음료","cat_small":"NON 커피"},{"item":"오케 주스","qty":10,"net":60000,"cat_big":"매장메뉴","cat_mid":"음료","cat_small":"에이드/주스/블렌디드"},{"item":"시트러스 주스","qty":4,"net":26000,"cat_big":"매장메뉴","cat_mid":"음료","cat_small":"에이드/주스/블렌디드"},{"item":"청포도라임에이드","qty":9,"net":54000,"cat_big":"매장메뉴","cat_mid":"음료","cat_small":"에이드/주스/블렌디드"},{"item":"인크선셋에이드","qty":9,"net":58500,"cat_big":"매장메뉴","cat_mid":"음료","cat_small":"에이드/주스/블렌디드"},{"item":"자몽에이드","qty":6,"net":33000,"cat_big":"매장메뉴","cat_mid":"음료","cat_small":"에이드/주스/블렌디드"},{"item":"레몬에이드","qty":4,"net":22000,"cat_big":"매장메뉴","cat_mid":"음료","cat_small":"에이드/주스/블렌디드"},{"item":"민트초코칩 블렌디드","qty":2,"net":12000,"cat_big":"매장메뉴","cat_mid":"음료","cat_small":"에이드/주스/블렌디드"},{"item":"쿠키앤크림 블렌디드","qty":3,"net":18000,"cat_big":"매장메뉴","cat_mid":"음료","cat_small":"에이드/주스/블렌디드"},{"item":"그린티 블렌디드","qty":4,"net":24000,"cat_big":"매장메뉴","cat_mid":"음료","cat_small":"에이드/주스/블렌디드"},{"item":"제주 한라봉 블렌디드","qty":8,"net":48000,"cat_big":"매장메뉴","cat_mid":"음료","cat_small":"에이드/주스/블렌디드"},{"item":"딸기바나나 블렌디드","qty":8,"net":48000,"cat_big":"매장메뉴","cat_mid":"음료","cat_small":"에이드/주스/블렌디드"},{"item":"딸기요거트","qty":11,"net":79200,"cat_big":"매장메뉴","cat_mid":"음료","cat_small":"시즌음료"},{"item":"인크메리베리","qty":8,"net":58400,"cat_big":"매장메뉴","cat_mid":"음료","cat_small":"시즌음료"},{"item":"딸기벨벳라떼","qty":14,"net":91000,"cat_big":"매장메뉴","cat_mid":"음료","cat_small":"시즌음료"},{"item":"핑크아포카토","qty":1,"net":7500,"cat_big":"매장메뉴","cat_mid":"음료","cat_small":"시즌음료"},{"item":"러블리레몬에이드","qty":1,"net":7000,"cat_big":"매장메뉴","cat_mid":"음료","cat_small":"시즌음료"},{"item":"밀크 아이스크림","qty":12,"net":45600,"cat_big":"매장메뉴","cat_mid":"음료","cat_small":"아이스크림"},{"item":"애플크럼블 아이스크림","qty":4,"net":17200,"cat_big":"매장메뉴","cat_mid":"음료","cat_small":"아이스크림"},{"item":"아메리카노","qty":2,"net":9000,"cat_big":"매장메뉴","cat_mid":"음료","cat_small":"얼라이브"},{"item":"플랫화이트","qty":2,"net":10000,"cat_big":"매장메뉴","cat_mid":"음료","cat_small":"얼라이브"},{"item":"All at Once","qty":2,"net":24000,"cat_big":"매장메뉴","cat_mid":"음료","cat_small":"얼라이브"},{"item":"마라카투라 푸어오버","qty":1,"net":6000,"cat_big":"매장메뉴","cat_mid":"음료","cat_small":"얼라이브"},{"item":"마라카투라 사이폰","qty":2,"net":13000,"cat_big":"매장메뉴","cat_mid":"음료","cat_small":"얼라이브"},{"item":"I 마라카투라 푸어오버","qty":1,"net":6000,"cat_big":"매장메뉴","cat_mid":"음료","cat_small":"얼라이브"},{"item":"I 디카페인 문보우 필터","qty":1,"net":7000,"cat_big":"매장메뉴","cat_mid":"음료","cat_small":"얼라이브"},{"item":"I 콜롬비아 토피","qty":1,"net":7500,"cat_big":"매장메뉴","cat_mid":"음료","cat_small":"얼라이브"},{"item":"I 콜롬비아 피나콜라다_사이폰","qty":1,"net":8000,"cat_big":"매장메뉴","cat_mid":"음료","cat_small":"얼라이브"},{"item":"콜롬비아 피나콜라다","qty":1,"net":7500,"cat_big":"매장메뉴","cat_mid":"음료","cat_small":"얼라이브"},{"item":"I 콜롬비아 피나콜라다","qty":1,"net":7500,"cat_big":"매장메뉴","cat_mid":"음료","cat_small":"얼라이브"},{"item":"에티오피아 모모라","qty":3,"net":16500,"cat_big":"매장메뉴","cat_mid":"음료","cat_small":"얼라이브"},{"item":"i 콜롬비아 프로즌_사이폰","qty":1,"net":8000,"cat_big":"매장메뉴","cat_mid":"음료","cat_small":"얼라이브"},{"item":"H 케냐 피베리 필터","qty":2,"net":12000,"cat_big":"매장메뉴","cat_mid":"음료","cat_small":"얼라이브"},{"item":"H 케냐 피베리 사이폰","qty":1,"net":6500,"cat_big":"매장메뉴","cat_mid":"음료","cat_small":"얼라이브"},{"item":"밤식빵","qty":9,"net":40500,"cat_big":"매장메뉴","cat_mid":"베이커리","cat_small":"브레드"},{"item":"생식빵(조각)","qty":5,"net":12500,"cat_big":"매장메뉴","cat_mid":"베이커리","cat_small":"브레드"},{"item":"탕종 토마토 식빵","qty":6,"net":27000,"cat_big":"매장메뉴","cat_mid":"베이커리","cat_small":"브레드"},{"item":"찹쌀 브리오슈 식빵","qty":6,"net":27000,"cat_big":"매장메뉴","cat_mid":"베이커리","cat_small":"브레드"},{"item":"단팥빵","qty":10,"net":25000,"cat_big":"매장메뉴","cat_mid":"베이커리","cat_small":"브레드"},{"item":"소보로","qty":10,"net":22000,"cat_big":"매장메뉴","cat_mid":"베이커리","cat_small":"브레드"},{"item":"흑임자 소보로","qty":20,"net":60000,"cat_big":"매장메뉴","cat_mid":"베이커리","cat_small":"브레드"},{"item":"어니언 크림치즈","qty":9,"net":40500,"cat_big":"매장메뉴","cat_mid":"베이커리","cat_small":"브레드"},{"item":"시오빵","qty":41,"net":102500,"cat_big":"매장메뉴","cat_mid":"베이커리","cat_small":"브레드"},{"item":"리얼초코초코","qty":18,"net":59400,"cat_big":"매장메뉴","cat_mid":"베이커리","cat_small":"브레드"},{"item":"육쪽 마늘빵","qty":10,"net":55000,"cat_big":"매장메뉴","cat_mid":"베이커리","cat_small":"브레드"},{"item":"버터 프레첼","qty":13,"net":52000,"cat_big":"매장메뉴","cat_mid":"베이커리","cat_small":"브레드"},{"item":"파마산 프레첼","qty":6,"net":24000,"cat_big":"매장메뉴","cat_mid":"베이커리","cat_small":"브레드"},{"item":"블랙트리플","qty":10,"net":45000,"cat_big":"매장메뉴","cat_mid":"베이커리","cat_small":"브레드"},{"item":"앙버터 바게트","qty":14,"net":63000,"cat_big":"매장메뉴","cat_mid":"베이커리","cat_small":"브레드"},{"item":"고르곤 치즈 바게트","qty":12,"net":57600,"cat_big":"매장메뉴","cat_mid":"베이커리","cat_small":"브레드"},{"item":"부추 치아바타","qty":10,"net":32000,"cat_big":"매장메뉴","cat_mid":"베이커리","cat_small":"브레드"},{"item":"먹물 롤치즈 치아바타","qty":10,"net":35000,"cat_big":"매장메뉴","cat_mid":"베이커리","cat_small":"브레드"},{"item":"베이컨치즈올리브 치아바타","qty":11,"net":41800,"cat_big":"매장메뉴","cat_mid":"베이커리","cat_small":"브레드"},{"item":"단호박빵","qty":7,"net":24500,"cat_big":"매장메뉴","cat_mid":"베이커리","cat_small":"브레드"},{"item":"INC 크림 모카","qty":12,"net":66000,"cat_big":"매장메뉴","cat_mid":"베이커리","cat_small":"브레드"},{"item":"모카빵","qty":8,"net":36000,"cat_big":"매장메뉴","cat_mid":"베이커리","cat_small":"브레드"},{"item":"모카번","qty":19,"net":66500,"cat_big":"매장메뉴","cat_mid":"베이커리","cat_small":"브레드"},{"item":"베이컨롤","qty":14,"net":56000,"cat_big":"매장메뉴","cat_mid":"베이커리","cat_small":"브레드"},{"item":"크로크무슈","qty":10,"net":40000,"cat_big":"매장메뉴","cat_mid":"베이커리","cat_small":"브레드"},{"item":"미니)밤식빵","qty":8,"net":24000,"cat_big":"매장메뉴","cat_mid":"베이커리","cat_small":"브레드"},{"item":"미니)찹쌀식빵","qty":6,"net":18000,"cat_big":"매장메뉴","cat_mid":"베이커리","cat_small":"브레드"},{"item":"미니)토마토식빵","qty":8,"net":26400,"cat_big":"매장메뉴","cat_mid":"베이커리","cat_small":"브레드"},{"item":"샐러드빵","qty":15,"net":75000,"cat_big":"매장메뉴","cat_mid":"베이커리","cat_small":"브레드"},{"item":"INC화이트모찌","qty":21,"net":73500,"cat_big":"매장메뉴","cat_mid":"베이커리","cat_small":"브레드"},{"item":"크로아상","qty":11,"net":38500,"cat_big":"매장메뉴","cat_mid":"베이커리","cat_small":"페스츄리"},{"item":"뺑 오 쇼콜라","qty":10,"net":40000,"cat_big":"매장메뉴","cat_mid":"베이커리","cat_small":"페스츄리"},{"item":"롱 소시지","qty":18,"net":81000,"cat_big":"매장메뉴","cat_mid":"베이커리","cat_small":"페스츄리"},{"item":"퀸아망 플레인","qty":12,"net":39600,"cat_big":"매장메뉴","cat_mid":"베이커리","cat_small":"페스츄리"},{"item":"큐브초코초코","qty":10,"net":48000,"cat_big":"매장메뉴","cat_mid":"베이커리","cat_small":"페스츄리"},{"item":"몽블랑(판매중단)","qty":9,"net":49500,"cat_big":"매장메뉴","cat_mid":"베이커리","cat_small":"페스츄리"},{"item":"뉴욕 초코","qty":8,"net":36000,"cat_big":"매장메뉴","cat_mid":"베이커리","cat_small":"페스츄리"},{"item":"맘모스(판매중지)","qty":9,"net":40500,"cat_big":"매장메뉴","cat_mid":"베이커리","cat_small":"페스츄리"},{"item":"뀌니아망 초코","qty":11,"net":38500,"cat_big":"매장메뉴","cat_mid":"베이커리","cat_small":"페스츄리"},{"item":"레몬크런치","qty":10,"net":55000,"cat_big":"매장메뉴","cat_mid":"베이커리","cat_small":"페스츄리"},{"item":"라즈베리크런치","qty":15,"net":82500,"cat_big":"매장메뉴","cat_mid":"베이커리","cat_small":"페스츄리"},{"item":"쌍쌍파이","qty":15,"net":60000,"cat_big":"매장메뉴","cat_mid":"베이커리","cat_small":"페스츄리"},{"item":"포레누아 케이크(P)","qty":8,"net":48000,"cat_big":"매장메뉴","cat_mid":"베이커리","cat_small":"케이크"},{"item":"자몽 오렌지(P)","qty":15,"net":90000,"cat_big":"매장메뉴","cat_mid":"베이커리","cat_small":"케이크"},{"item":"흑임자롤","qty":10,"net":40000,"cat_big":"매장메뉴","cat_mid":"베이커리","cat_small":"케이크"},{"item":"딸기생크림","qty":56,"net":420000,"cat_big":"매장메뉴","cat_mid":"베이커리","cat_small":"케이크"},{"item":"당근케이크","qty":9,"net":63000,"cat_big":"매장메뉴","cat_mid":"베이커리","cat_small":"케이크"},{"item":"레몬 파운드","qty":17,"net":59500,"cat_big":"매장메뉴","cat_mid":"베이커리","cat_small":"구움과자"},{"item":"얼그레이 파운드","qty":12,"net":42000,"cat_big":"매장메뉴","cat_mid":"베이커리","cat_small":"구움과자"},{"item":"더블초콜릿 쿠키","qty":6,"net":21000,"cat_big":"매장메뉴","cat_mid":"베이커리","cat_small":"구움과자"},{"item":"크랜베리아몬드 쿠키","qty":2,"net":6000,"cat_big":"매장메뉴","cat_mid":"베이커리","cat_small":"구움과자"},{"item":"플레인 휘낭시에","qty":11,"net":33000,"cat_big":"매장메뉴","cat_mid":"베이커리","cat_small":"구움과자"},{"item":"소금초코 휘낭시에","qty":15,"net":52500,"cat_big":"매장메뉴","cat_mid":"베이커리","cat_small":"구움과자"},{"item":"헤이즐넛 오렌지 휘낭시에","qty":9,"net":27000,"cat_big":"매장메뉴","cat_mid":"베이커리","cat_small":"구움과자"},{"item":"레몬 마들렌","qty":13,"net":39000,"cat_big":"매장메뉴","cat_mid":"베이커리","cat_small":"구움과자"},{"item":"초코 마들렌","qty":6,"net":21000,"cat_big":"매장메뉴","cat_mid":"베이커리","cat_small":"구움과자"},{"item":"쑥 마들렌","qty":4,"net":14000,"cat_big":"매장메뉴","cat_mid":"베이커리","cat_small":"구움과자"},{"item":"커피피칸 마들렌","qty":7,"net":21000,"cat_big":"매장메뉴","cat_mid":"베이커리","cat_small":"구움과자"},{"item":"생크림 스콘","qty":8,"net":28000,"cat_big":"매장메뉴","cat_mid":"베이커리","cat_small":"구움과자"},{"item":"흑임자스노우볼","qty":2,"net":11000,"cat_big":"매장메뉴","cat_mid":"베이커리","cat_small":"구움과자"},{"item":"원통)쇼콜라 프로겐트","qty":1,"net":5500,"cat_big":"매장메뉴","cat_mid":"베이커리","cat_small":"구움과자"},{"item":"원통)카카오닙스쿠키","qty":1,"net":5500,"cat_big":"매장메뉴","cat_mid":"베이커리","cat_small":"구움과자"},{"item":"갸토 쇼콜라","qty":7,"net":49000,"cat_big":"매장메뉴","cat_mid":"베이커리","cat_small":"구움과자"},{"item":"와이드 마우스 오렌지 16oz","qty":1,"net":36000,"cat_big":"매장메뉴","cat_mid":"MD","cat_small":"텀블러"},{"item":"에디오피아 블랜드 200g","qty":3,"net":39000,"cat_big":"매장메뉴","cat_mid":"MD","cat_small":"커피류"},{"item":"인크 베이직 블랜드 200g","qty":3,"net":33000,"cat_big":"매장메뉴","cat_mid":"MD","cat_small":"커피류"},{"item":"에디오피아 단세모모라 200g","qty":1,"net":13000,"cat_big":"매장메뉴","cat_mid":"MD","cat_small":"커피류"},{"item":"에디오피아 구지 G1 200g","qty":2,"net":26000,"cat_big":"매장메뉴","cat_mid":"MD","cat_small":"커피류"},{"item":"케냐 피베리 200g","qty":2,"net":28000,"cat_big":"매장메뉴","cat_mid":"MD","cat_small":"커피류"},{"item":"드립백(에디오피아)","qty":1,"net":12000,"cat_big":"매장메뉴","cat_mid":"MD","cat_small":"커피류"},{"item":"드립백(베이직)","qty":3,"net":33000,"cat_big":"매장메뉴","cat_mid":"MD","cat_small":"커피류"},{"item":"베이직 블렌드 1kg","qty":1,"net":38500,"cat_big":"매장메뉴","cat_mid":"MD","cat_small":"커피류"},{"item":"new오렌지쇼핑백","qty":2,"net":1000,"cat_big":"매장메뉴","cat_mid":"MD","cat_small":"커피류"},{"item":"우드쟁반","qty":1,"net":45000,"cat_big":"매장메뉴","cat_mid":"MD","cat_small":"테이블웨어"},{"item":"오케잼","qty":1,"net":11000,"cat_big":"매장메뉴","cat_mid":"MD","cat_small":"기타"},{"item":"블루베리잼","qty":1,"net":10000,"cat_big":"매장메뉴","cat_mid":"MD","cat_small":"기타"},{"item":"증정)인크포스터달력","qty":3,"net":0,"cat_big":"매장메뉴","cat_mid":"MD","cat_small":"기타"},{"item":"크라프트쇼핑백","qty":4,"net":800,"cat_big":"매장메뉴","cat_mid":"MD","cat_small":"기타"},{"item":"바이트 박스","qty":1,"net":1000,"cat_big":"매장메뉴","cat_mid":"MD","cat_small":"포장"},{"item":"기프트카드2","qty":2,"net":60000,"cat_big":"매장메뉴","cat_mid":"기타","cat_small":"기프트카드"},{"item":"기프트카드3","qty":2,"net":100000,"cat_big":"매장메뉴","cat_mid":"기타","cat_small":"기프트카드"},{"item":"10,000원","qty":4,"net":40000,"cat_big":"매장메뉴","cat_mid":"기타","cat_small":"특판"},{"item":"원두 분쇄(드립용)","qty":2,"net":0,"cat_big":"매장메뉴","cat_mid":"기타","cat_small":"특판"},{"item":"머그잔","qty":78,"net":0,"cat_big":"요청사항","cat_mid":"요청","cat_small":"요청"},{"item":"투고컵","qty":16,"net":0,"cat_big":"요청사항","cat_mid":"요청","cat_small":"요청"},{"item":"연하게","qty":28,"net":0,"cat_big":"요청사항","cat_mid":"요청","cat_small":"요청"},{"item":"얼음 적게","qty":1,"net":0,"cat_big":"요청사항","cat_mid":"요청","cat_small":"요청"},{"item":"캐리어","qty":6,"net":0,"cat_big":"요청사항","cat_mid":"요청","cat_small":"요청"},{"item":"베이커리 커팅","qty":1,"net":0,"cat_big":"요청사항","cat_mid":"요청","cat_small":"요청"},{"item":"진동벨 7","qty":1,"net":0,"cat_big":"요청사항","cat_mid":"진동벨","cat_small":"진동벨 넘버"},{"item":"진동벨 11","qty":1,"net":0,"cat_big":"요청사항","cat_mid":"진동벨","cat_small":"진동벨 넘버"},{"item":"진동벨 22","qty":1,"net":0,"cat_big":"요청사항","cat_mid":"진동벨","cat_small":"진동벨 넘버"},{"item":"진동벨 26","qty":2,"net":0,"cat_big":"요청사항","cat_mid":"진동벨","cat_small":"진동벨 넘버"},{"item":"진동벨 36","qty":2,"net":0,"cat_big":"요청사항","cat_mid":"진동벨","cat_small":"진동벨 넘버"},{"item":"진동벨 38","qty":2,"net":0,"cat_big":"요청사항","cat_mid":"진동벨","cat_small":"진동벨 넘버"},{"item":"진동벨 39","qty":1,"net":0,"cat_big":"요청사항","cat_mid":"진동벨","cat_small":"진동벨 넘버"},{"item":"진동벨 46","qty":1,"net":0,"cat_big":"요청사항","cat_mid":"진동벨","cat_small":"진동벨 넘버"},{"item":"진동벨 48","qty":1,"net":0,"cat_big":"요청사항","cat_mid":"진동벨","cat_small":"진동벨 넘버"},{"item":"진동벨 49","qty":2,"net":0,"cat_big":"요청사항","cat_mid":"진동벨","cat_small":"진동벨 넘버"}]}}