{"items":[{"store":"가산","item":"드립백(타이거즈)","qty":4,"net":48000,"cat_big":"MD/기타","cat_mid":"MD","cat_small":"커피류"},{"store":"가산","item":"인크커피믹스(30입)","qty":3,"net":36000,"cat_big":"MD/기타","cat_mid":"MD","cat_small":"커피류"},{"store":"가산","item":"콜롬비아 커피백(페도라형)","qty":39,"net":78000,"cat_big":"MD/기타","cat_mid":"MD","cat_small":"커피류"},{"store":"가산","item":"론자카파 럼배럴 에이지드 200g","qty":15,"net":495000,"cat_big":"MD/기타","cat_mid":"MD","cat_small":"커피류"},{"store":"가산","item":"COL 산추아리오 골드워시드 20g(after)","qty":2,"net":4000,"cat_big":"MD/기타","cat_mid":"MD","cat_small":"커피류"},{"store":"가산","item":"인크 오리진블렌드 1Kg","qty":3,"net":168000,"cat_big":"MD/기타","cat_mid":"MD","cat_small":"커피류"},{"store":"가산","item":"다크 오리진블렌드 200g","qty":15,"net":240000,"cat_big":"MD/기타","cat_mid":"MD","cat_small":"커피류"},{"store":"가산","item":"COL 캄포 에르모소(VH) 20g","qty":5,"net":15000,"cat_big":"MD/기타","cat_mid":"MD","cat_small":"커피류"},{"store":"가산","item":"ETH 예가체프 코케허니G1(N)200g","qty":39,"net":721500,"cat_big":"MD/기타","cat_mid":"MD","cat_small":"커피류"},{"store":"가산","item":"인크 스퀘어 글라스 머그 INC","qty":1,"net":11000,"cat_big":"MD/기타","cat_mid":"MD","cat_small":"테이블웨어"},{"store":"가산","item":"쇼핑백(NEW오렌지)","qty":44,"net":44000,"cat_big":"MD/기타","cat_mid":"MD","cat_small":"포장"},{"store":"가산","item":"바이트 박스","qty":20,"net":20000,"cat_big":"MD/기타","cat_mid":"MD","cat_small":"포장"},{"store":"가산","item":"크라프트 쇼핑백","qty":169,"net":33800,"cat_big":"MD/기타","cat_mid":"MD","cat_small":"포장"},{"store":"가산","item":"DRIP BAG VARIETY BOX","qty":22,"net":550000,"cat_big":"MD/기타","cat_mid":"MD","cat_small":"선물세트"},{"store":"가산","item":"커피백 머그세트","qty":5,"net":160000,"cat_big":"MD/기타","cat_mid":"MD","cat_small":"선물세트"},{"store":"가산","item":"자카파_밀크","qty":531,"net":4248000,"cat_big":"음료","cat_mid":"공통","cat_small":"시그니처"},{"store":"가산","item":"아메리카노(R)","qty":194,"net":1319200,"cat_big":"음료","cat_mid":"공통","cat_small":"시그니처"},{"store":"가산","item":"I 아메리카노(R)","qty":790,"net":5372000,"cat_big":"음료","cat_mid":"공통","cat_small":"시그니처"},{"store":"가산","item":"카페라떼(R)","qty":102,"net":693600,"cat_big":"음료","cat_mid":"공통","cat_small":"시그니처"},{"store":"가산","item":"I 카페라떼(R)","qty":217,"net":1475600,"cat_big":"음료","cat_mid":"공통","cat_small":"시그니처"},{"store":"가산","item":"콜롬비아 산추아리오 골드워시드","qty":12,"net":84000,"cat_big":"음료","cat_mid":"공통","cat_small":"드립커피"},{"store":"가산","item":"과테말라 럼배럴","qty":34,"net":272000,"cat_big":"음료","cat_mid":"공통","cat_small":"드립커피"},{"store":"가산","item":"I 과테말라 럼배럴","qty":75,"net":600000,"cat_big":"음료","cat_mid":"공통","cat_small":"드립커피"},{"store":"가산","item":"H 콜롬비아 에르모소","qty":20,"net":140000,"cat_big":"음료","cat_mid":"공통","cat_small":"드립커피"},{"store":"가산","item":"H 엘살바도르 파카마라 내추럴","qty":32,"net":208000,"cat_big":"음료","cat_mid":"공통","cat_small":"드립커피"},{"store":"가산","item":"I 엘살바도르 파카마라 내추럴","qty":42,"net":273000,"cat_big":"음료","cat_mid":"공통","cat_small":"드립커피"},{"store":"가산","item":"H 에티오피아 코케허니","qty":98,"net":637000,"cat_big":"음료","cat_mid":"공통","cat_small":"드립커피"},{"store":"가산","item":"I 에티오피아 코케허니","qty":114,"net":741000,"cat_big":"음료","cat_mid":"공통","cat_small":"드립커피"},{"store":"가산","item":"과테말라 럼배럴(SP)","qty":16,"net":160000,"cat_big":"음료","cat_mid":"공통","cat_small":"싸이폰"},{"store":"가산","item":"H 에티오피아 코케허니(SP)","qty":3,"net":24000,"cat_big":"음료","cat_mid":"공통","cat_small":"싸이폰"},{"store":"가산","item":"아메리카노(D)","qty":241,"net":1301400,"cat_big":"음료","cat_mid":"공통","cat_small":"커피"},{"store":"가산","item":"아메리카노(INC)","qty":603,"net":3256200,"cat_big":"음료","cat_mid":"공통","cat_small":"커피"},{"store":"가산","item":"아메리카노(DARK)","qty":497,"net":2683800,"cat_big":"음료","cat_mid":"공통","cat_small":"커피"},{"store":"가산","item":"I 아메리카노(D)","qty":730,"net":3942000,"cat_big":"음료","cat_mid":"공통","cat_small":"커피"},{"store":"가산","item":"I 아메리카노(INC)","qty":1875,"net":10125000,"cat_big":"음료","cat_mid":"공통","cat_small":"커피"},{"store":"가산","item":"I 아메리카노(DARK)","qty":1828,"net":9871200,"cat_big":"음료","cat_mid":"공통","cat_small":"커피"},{"store":"가산","item":"아메리카노_UP(DARK)","qty":16,"net":94400,"cat_big":"음료","cat_mid":"공통","cat_small":"커피"},{"store":"가산","item":"I 아메리카노_UP(D)","qty":53,"net":312700,"cat_big":"음료","cat_mid":"공통","cat_small":"커피"},{"store":"가산","item":"I 아메리카노_UP(INC)","qty":205,"net":1209500,"cat_big":"음료","cat_mid":"공통","cat_small":"커피"},{"store":"가산","item":"I 아메리카노_UP(DARK)","qty":229,"net":1351100,"cat_big":"음료","cat_mid":"공통","cat_small":"커피"},{"store":"가산","item":"플랫 화이트","qty":124,"net":719200,"cat_big":"음료","cat_mid":"공통","cat_small":"커피"},{"store":"가산","item":"I 플랫 화이트","qty":140,"net":812000,"cat_big":"음료","cat_mid":"공통","cat_small":"커피"},{"store":"가산","item":"카페 라떼","qty":527,"net":3056600,"cat_big":"음료","cat_mid":"공통","cat_small":"커피"},{"store":"가산","item":"I 카페 라떼","qty":799,"net":4634200,"cat_big":"음료","cat_mid":"공통","cat_small":"커피"},{"store":"가산","item":"연유 라떼","qty":31,"net":201500,"cat_big":"음료","cat_mid":"공통","cat_small":"커피"},{"store":"가산","item":"I 연유 라떼","qty":136,"net":884000,"cat_big":"음료","cat_mid":"공통","cat_small":"커피"},{"store":"가산","item":"바닐라빈 라떼","qty":81,"net":526500,"cat_big":"음료","cat_mid":"공통","cat_small":"커피"},{"store":"가산","item":"I 바닐라빈 라떼","qty":298,"net":1937000,"cat_big":"음료","cat_mid":"공통","cat_small":"커피"},{"store":"가산","item":"I 카페 모카","qty":43,"net":279500,"cat_big":"음료","cat_mid":"공통","cat_small":"커피"},{"store":"가산","item":"쿠키앤크림 블렌디드","qty":122,"net":915000,"cat_big":"음료","cat_mid":"공통","cat_small":"블랜디드"},{"store":"가산","item":"제주 한라봉 블랜디드","qty":243,"net":1822500,"cat_big":"음료","cat_mid":"공통","cat_small":"블랜디드"},{"store":"가산","item":"자몽 에이드","qty":100,"net":750000,"cat_big":"음료","cat_mid":"공통","cat_small":"에이드"},{"store":"가산","item":"청포도 라임 에이드","qty":148,"net":1110000,"cat_big":"음료","cat_mid":"공통","cat_small":"에이드"},{"store":"가산","item":"시트러스 주스","qty":195,"net":1462500,"cat_big":"음료","cat_mid":"공통","cat_small":"주스"},{"store":"가산","item":"문경 사과 주스","qty":285,"net":2137500,"cat_big":"음료","cat_mid":"공통","cat_small":"주스"},{"store":"가산","item":"I 초코 라떼","qty":153,"net":1040400,"cat_big":"음료","cat_mid":"공통","cat_small":"논커피"},{"store":"가산","item":"제주 말차 라떼","qty":75,"net":510000,"cat_big":"음료","cat_mid":"공통","cat_small":"논커피"},{"store":"가산","item":"I 제주 말차 라떼","qty":281,"net":1910800,"cat_big":"음료","cat_mid":"공통","cat_small":"논커피"},{"store":"가산","item":"밀크티","qty":54,"net":367200,"cat_big":"음료","cat_mid":"공통","cat_small":"논커피"},{"store":"가산","item":"I 밀크티","qty":155,"net":1054000,"cat_big":"음료","cat_mid":"공통","cat_small":"논커피"},{"store":"가산","item":"밀크 아이스크림","qty":143,"net":686400,"cat_big":"음료","cat_mid":"공통","cat_small":"논커피"},{"store":"가산","item":"세러니티","qty":140,"net":812000,"cat_big":"음료","cat_mid":"공통","cat_small":"차"},{"store":"가산","item":"I 세러니티","qty":105,"net":609000,"cat_big":"음료","cat_mid":"공통","cat_small":"차"},{"store":"가산","item":"크림슨펀치","qty":73,"net":423400,"cat_big":"음료","cat_mid":"공통","cat_small":"차"},{"store":"가산","item":"I 크림슨펀치","qty":87,"net":504600,"cat_big":"음료","cat_mid":"공통","cat_small":"차"},{"store":"가산","item":"I 겐마이차","qty":27,"net":156600,"cat_big":"음료","cat_mid":"공통","cat_small":"차"},{"store":"가산","item":"얼그레이","qty":41,"net":237800,"cat_big":"음료","cat_mid":"공통","cat_small":"차"},{"store":"가산","item":"I 얼그레이","qty":43,"net":249400,"cat_big":"음료","cat_mid":"공통","cat_small":"차"},{"store":"가산","item":"피치우롱","qty":93,"net":539400,"cat_big":"음료","cat_mid":"공통","cat_small":"차"},{"store":"가산","item":"I 피치우롱","qty":167,"net":968600,"cat_big":"음료","cat_mid":"공통","cat_small":"차"},{"store":"가산","item":"I 애플 시나몬 세러니티","qty":84,"net":546000,"cat_big":"음료","cat_mid":"스페셜","cat_small":"시즌음료"},{"store":"가산","item":"얼그레이 그린플럼티","qty":131,"net":851500,"cat_big":"음료","cat_mid":"스페셜","cat_small":"시즌음료"},{"store":"가산","item":"럼 마론 크림 라떼","qty":122,"net":976000,"cat_big":"음료","cat_mid":"스페셜","cat_small":"시즌음료"},{"store":"가산","item":"콘 크러쉬 블렌디드","qty":91,"net":527800,"cat_big":"음료","cat_mid":"공통","cat_small":"블랜디드"},{"store":"가산","item":"애플 시나몬 크럼블 아이스크림 추가","qty":112,"net":112000,"cat_big":"음료","cat_mid":"스페셜","cat_small":"시즌음료"},{"store":"가산","item":"레몬 마들렌","qty":81,"net":307800,"cat_big":"베이커리","cat_mid":"구움과자","cat_small":"마들렌"},{"store":"가산","item":"초콜릿 마들렌","qty":36,"net":136800,"cat_big":"베이커리","cat_mid":"구움과자","cat_small":"마들렌"},{"store":"가산","item":"커피 피칸 마들렌","qty":22,"net":77000,"cat_big":"베이커리","cat_mid":"구움과자","cat_small":"마들렌"},{"store":"가산","item":"라임 바질 마들렌","qty":13,"net":49400,"cat_big":"베이커리","cat_mid":"구움과자","cat_small":"마들렌"},{"store":"가산","item":"크런치 땅콩 마들렌","qty":26,"net":91000,"cat_big":"베이커리","cat_mid":"구움과자","cat_small":"마들렌"},{"store":"가산","item":"레몬 버터 바","qty":104,"net":395200,"cat_big":"베이커리","cat_mid":"구움과자","cat_small":"버터바"},{"store":"가산","item":"피넛 버터 바","qty":81,"net":307800,"cat_big":"베이커리","cat_mid":"구움과자","cat_small":"버터바"},{"store":"가산","item":"애플잼 스콘","qty":348,"net":1740000,"cat_big":"베이커리","cat_mid":"구움과자","cat_small":"스콘"},{"store":"가산","item":"레몬 파운드","qty":73,"net":328500,"cat_big":"베이커리","cat_mid":"구움과자","cat_small":"파운드"},{"store":"가산","item":"얼 그레이 파운드","qty":54,"net":243000,"cat_big":"베이커리","cat_mid":"구움과자","cat_small":"파운드"},{"store":"가산","item":"플레인 휘낭시에","qty":58,"net":220400,"cat_big":"베이커리","cat_mid":"구움과자","cat_small":"휘낭시에"},{"store":"가산","item":"소금 초콜릿 휘낭시에","qty":75,"net":300000,"cat_big":"베이커리","cat_mid":"구움과자","cat_small":"휘낭시에"},{"store":"가산","item":"다크 망디앙 휘낭시에","qty":36,"net":172800,"cat_big":"베이커리","cat_mid":"구움과자","cat_small":"휘낭시에"},{"store":"가산","item":"화이트 망디앙 휘낭시에","qty":37,"net":177600,"cat_big":"베이커리","cat_mid":"구움과자","cat_small":"휘낭시에"},{"store":"가산","item":"얼 그레이 휘낭시에","qty":67,"net":268000,"cat_big":"베이커리","cat_mid":"구움과자","cat_small":"휘낭시에"},{"store":"가산","item":"무화과 크림 치즈 휘낭시에","qty":66,"net":250800,"cat_big":"베이커리","cat_mid":"구움과자","cat_small":"휘낭시에"},{"store":"가산","item":"애플 시나몬 크럼블","qty":241,"net":1325500,"cat_big":"베이커리","cat_mid":"구움과자","cat_small":"크럼블"},{"store":"가산","item":"올리브 에멘탈 치즈 사워도우","qty":203,"net":1055600,"cat_big":"베이커리","cat_mid":"브레드","cat_small":"건강빵"},{"store":"가산","item":"사워도우(단품)","qty":50,"net":200000,"cat_big":"베이커리","cat_mid":"브레드","cat_small":"건강빵"},{"store":"가산","item":"미니 무화과 샤워도우","qty":365,"net":1387000,"cat_big":"베이커리","cat_mid":"브레드","cat_small":"건강빵"},{"store":"가산","item":"라우겐 베이글","qty":286,"net":1287000,"cat_big":"베이커리","cat_mid":"브레드","cat_small":"베이글"},{"store":"가산","item":"치즈 포테이토 베이글","qty":158,"net":948000,"cat_big":"베이커리","cat_mid":"브레드","cat_small":"베이글"},{"store":"가산","item":"버터 라우겐 베이글","qty":195,"net":1209000,"cat_big":"베이커리","cat_mid":"브레드","cat_small":"베이글"},{"store":"가산","item":"쪽파 크림 치즈 베이글","qty":302,"net":2265000,"cat_big":"베이커리","cat_mid":"브레드","cat_small":"베이글"},{"store":"가산","item":"올리브 베이글","qty":141,"net":592200,"cat_big":"베이커리","cat_mid":"브레드","cat_small":"베이글"},{"store":"가산","item":"모카 베이글","qty":162,"net":842400,"cat_big":"베이커리","cat_mid":"브레드","cat_small":"베이글"},{"store":"가산","item":"에그 샌드위치","qty":129,"net":838500,"cat_big":"베이커리","cat_mid":"브레드","cat_small":"샌드위치"},{"store":"가산","item":"크루아상 잠봉 샌드위치","qty":179,"net":1396200,"cat_big":"베이커리","cat_mid":"브레드","cat_small":"샌드위치"},{"store":"가산","item":"플레인 소금빵","qty":726,"net":3049200,"cat_big":"베이커리","cat_mid":"브레드","cat_small":"소금빵"},{"store":"가산","item":"갈릭 소금빵","qty":167,"net":801600,"cat_big":"베이커리","cat_mid":"브레드","cat_small":"소금빵"},{"store":"가산","item":"우유 크림 소금빵","qty":339,"net":1695000,"cat_big":"베이커리","cat_mid":"브레드","cat_small":"소금빵"},{"store":"가산","item":"앙버터 소금빵","qty":279,"net":1450800,"cat_big":"베이커리","cat_mid":"브레드","cat_small":"소금빵"},{"store":"가산","item":"명란 소금빵","qty":372,"net":1785600,"cat_big":"베이커리","cat_mid":"브레드","cat_small":"소금빵"},{"store":"가산","item":"수제 단팥빵","qty":175,"net":665000,"cat_big":"베이커리","cat_mid":"브레드","cat_small":"일반빵"},{"store":"가산","item":"흑임자 우유 크림 브레드","qty":118,"net":590000,"cat_big":"베이커리","cat_mid":"브레드","cat_small":"일반빵"},{"store":"가산","item":"소금빵 러스크","qty":9,"net":46800,"cat_big":"베이커리","cat_mid":"브레드","cat_small":"일반빵"},{"store":"가산","item":"밤 식빵","qty":159,"net":1113000,"cat_big":"베이커리","cat_mid":"브레드","cat_small":"일반빵"},{"store":"가산","item":"인크 로쉐","qty":256,"net":1484800,"cat_big":"베이커리","cat_mid":"브레드","cat_small":"일반빵"},{"store":"가산","item":"블루베리 크림 치즈","qty":19,"net":57000,"cat_big":"베이커리","cat_mid":"스프레드/잼/오일","cat_small":"크림 치즈"},{"store":"가산","item":"썸머 시트러스(조각)","qty":168,"net":1596000,"cat_big":"베이커리","cat_mid":"케이크","cat_small":"조각 케이크"},{"store":"가산","item":"뉴욕 치즈 케이크(조각)","qty":142,"net":1207000,"cat_big":"베이커리","cat_mid":"케이크","cat_small":"조각 케이크"},{"store":"가산","item":"무화과 생크림 케이크 (조각)","qty":583,"net":5538500,"cat_big":"베이커리","cat_mid":"케이크","cat_small":"조각 케이크"},{"store":"가산","item":"몽블랑 (조각)","qty":320,"net":3040000,"cat_big":"베이커리","cat_mid":"케이크","cat_small":"조각 케이크"},{"store":"가산","item":"무화과 생크림 케이크 (1호)","qty":26,"net":1118000,"cat_big":"베이커리","cat_mid":"케이크","cat_small":"홀 케이크"},{"store":"가산","item":"얼 그레이 무화과 데니쉬","qty":302,"net":2265000,"cat_big":"베이커리","cat_mid":"페이스트리","cat_small":"데니쉬"},{"store":"가산","item":"썸머 후르츠 데니쉬","qty":89,"net":667500,"cat_big":"베이커리","cat_mid":"페이스트리","cat_small":"데니쉬"},{"store":"가산","item":"플레인 퀸 아망","qty":271,"net":1300800,"cat_big":"베이커리","cat_mid":"페이스트리","cat_small":"퀸 아망"},{"store":"가산","item":"초콜릿 퀸 아망","qty":164,"net":852800,"cat_big":"베이커리","cat_mid":"페이스트리","cat_small":"퀸 아망"},{"store":"가산","item":"피스타치오 퀸 아망","qty":224,"net":1344000,"cat_big":"베이커리","cat_mid":"페이스트리","cat_small":"퀸 아망"},{"store":"가산","item":"두바이 퀸 아망","qty":263,"net":1525400,"cat_big":"베이커리","cat_mid":"페이스트리","cat_small":"퀸 아망"},{"store":"가산","item":"크룽지","qty":156,"net":702000,"cat_big":"베이커리","cat_mid":"페이스트리","cat_small":"크루아상 계열"},{"store":"가산","item":"뺑 오 쇼콜라","qty":156,"net":811200,"cat_big":"베이커리","cat_mid":"페이스트리","cat_small":"크루아상 계열"},{"store":"가산","item":"스리라차 소시지 페이스트리","qty":265,"net":1643000,"cat_big":"베이커리","cat_mid":"페이스트리","cat_small":"크루아상 계열"},{"store":"가산","item":"몽블랑 데니쉬","qty":149,"net":923800,"cat_big":"베이커리","cat_mid":"페이스트리","cat_small":"데니쉬"},{"store":"가산","item":"애플 턴오버","qty":143,"net":929500,"cat_big":"베이커리","cat_mid":"페이스트리","cat_small":"크루아상 계열"},{"store":"가산","item":"초콜릿 크룽지","qty":155,"net":744000,"cat_big":"베이커리","cat_mid":"페이스트리","cat_small":"크루아상 계열"},{"store":"가산","item":"햄치즈 그릴 샌드위치","qty":73,"net":1022000,"cat_big":"푸드","cat_mid":"가산 푸드","cat_small":"브런치"},{"store":"가산","item":"치킨 페스토 그릴 샌드위치","qty":67,"net":938000,"cat_big":"푸드","cat_mid":"가산 푸드","cat_small":"브런치"},{"store":"다산","item":"유기농 주스(애플디노)","qty":69,"net":172500,"cat_big":"RTD","cat_mid":"음료","cat_small":"RTD음료"},{"store":"다산","item":"뽀로로음료(딸기)","qty":73,"net":182500,"cat_big":"RTD","cat_mid":"음료","cat_small":"RTD음료"},{"store":"다산","item":"인크로쉐","qty":351,"net":2035800,"cat_big":"베이커리","cat_mid":"브레드","cat_small":"일반빵"},{"store":"다산","item":"올에브리띵 크림치즈 베이글","qty":102,"net":693600,"cat_big":"베이커리","cat_mid":"베이커리","cat_small":"베이글"},{"store":"다산","item":"인크 오리진블렌드 200g","qty":13,"net":208000,"cat_big":"MD/기타","cat_mid":"MD","cat_small":"커피류"},{"store":"다산","item":"쇼핑백(NEW오렌지)","qty":5,"net":5000,"cat_big":"MD/기타","cat_mid":"MD","cat_small":"포장"},{"store":"다산","item":"오렌지쇼핑백","qty":4,"net":2000,"cat_big":"MD/기타","cat_mid":"MD","cat_small":"포장"},{"store":"다산","item":"쇼핑백(감광지화이트)","qty":237,"net":47400,"cat_big":"MD/기타","cat_mid":"MD","cat_small":"포장"},{"store":"다산","item":"기프트카드2","qty":8,"net":240000,"cat_big":"MD/기타","cat_mid":"기타","cat_small":"기프트카드"},{"store":"다산","item":"기프트카드4","qty":5,"net":500000,"cat_big":"MD/기타","cat_mid":"기타","cat_small":"기프트카드"},{"store":"다산","item":"에비앙 500","qty":22,"net":55000,"cat_big":"RTD","cat_mid":"음료","cat_small":"RTD음료"},{"store":"다산","item":"자카파_밀크","qty":567,"net":4536000,"cat_big":"음료","cat_mid":"공통","cat_small":"시그니처"},{"store":"다산","item":"I 아메리카노(R)","qty":312,"net":2121600,"cat_big":"음료","cat_mid":"공통","cat_small":"시그니처"},{"store":"다산","item":"카페라떼(R)","qty":68,"net":462400,"cat_big":"음료","cat_mid":"공통","cat_small":"시그니처"},{"store":"다산","item":"과테말라 럼배럴","qty":30,"net":240000,"cat_big":"음료","cat_mid":"공통","cat_small":"드립커피"},{"store":"다산","item":"I 과테말라 럼배럴","qty":32,"net":256000,"cat_big":"음료","cat_mid":"공통","cat_small":"드립커피"},{"store":"다산","item":"I 엘살바도르 파카마라 내추럴","qty":33,"net":214500,"cat_big":"음료","cat_mid":"공통","cat_small":"드립커피"},{"store":"다산","item":"H 에티오피아 코케허니","qty":60,"net":390000,"cat_big":"음료","cat_mid":"공통","cat_small":"드립커피"},{"store":"다산","item":"I 에티오피아 코케허니","qty":85,"net":552500,"cat_big":"음료","cat_mid":"공통","cat_small":"드립커피"},{"store":"다산","item":"에스프레소(INC)","qty":12,"net":64800,"cat_big":"음료","cat_mid":"공통","cat_small":"커피"},{"store":"다산","item":"아메리카노(D)","qty":458,"net":2473200,"cat_big":"음료","cat_mid":"공통","cat_small":"커피"},{"store":"다산","item":"아메리카노(INC)","qty":976,"net":5270400,"cat_big":"음료","cat_mid":"공통","cat_small":"커피"},{"store":"다산","item":"아메리카노(DARK)","qty":1663,"net":8980200,"cat_big":"음료","cat_mid":"공통","cat_small":"커피"},{"store":"다산","item":"I 아메리카노(D)","qty":903,"net":4876200,"cat_big":"음료","cat_mid":"공통","cat_small":"커피"},{"store":"다산","item":"I 아메리카노(INC)","qty":1931,"net":10427400,"cat_big":"음료","cat_mid":"공통","cat_small":"커피"},{"store":"다산","item":"I 아메리카노(DARK)","qty":3705,"net":20007000,"cat_big":"음료","cat_mid":"공통","cat_small":"커피"},{"store":"다산","item":"I 아메리카노_UP(D)","qty":61,"net":359900,"cat_big":"음료","cat_mid":"공통","cat_small":"커피"},{"store":"다산","item":"I 아메리카노_UP(INC)","qty":150,"net":885000,"cat_big":"음료","cat_mid":"공통","cat_small":"커피"},{"store":"다산","item":"I 아메리카노_UP(DARK)","qty":318,"net":1876200,"cat_big":"음료","cat_mid":"공통","cat_small":"커피"},{"store":"다산","item":"플랫 화이트","qty":190,"net":1102000,"cat_big":"음료","cat_mid":"공통","cat_small":"커피"},{"store":"다산","item":"I 플랫 화이트","qty":125,"net":725000,"cat_big":"음료","cat_mid":"공통","cat_small":"커피"},{"store":"다산","item":"카페 라떼","qty":1058,"net":6136400,"cat_big":"음료","cat_mid":"공통","cat_small":"커피"},{"store":"다산","item":"I 카페 라떼","qty":1267,"net":7348600,"cat_big":"음료","cat_mid":"공통","cat_small":"커피"},{"store":"다산","item":"연유 라떼","qty":66,"net":429000,"cat_big":"음료","cat_mid":"공통","cat_small":"커피"},{"store":"다산","item":"바닐라빈 라떼","qty":240,"net":1560000,"cat_big":"음료","cat_mid":"공통","cat_small":"커피"},{"store":"다산","item":"I 바닐라빈 라떼","qty":708,"net":4602000,"cat_big":"음료","cat_mid":"공통","cat_small":"커피"},{"store":"다산","item":"I 카라멜 마끼아또","qty":75,"net":487500,"cat_big":"음료","cat_mid":"공통","cat_small":"커피"},{"store":"다산","item":"쿠키앤크림 블렌디드","qty":196,"net":1470000,"cat_big":"음료","cat_mid":"공통","cat_small":"블랜디드"},{"store":"다산","item":"제주 한라봉 블랜디드","qty":372,"net":2790000,"cat_big":"음료","cat_mid":"공통","cat_small":"블랜디드"},{"store":"다산","item":"자몽 에이드","qty":290,"net":2175000,"cat_big":"음료","cat_mid":"공통","cat_small":"에이드"},{"store":"다산","item":"청포도 라임 에이드","qty":372,"net":2790000,"cat_big":"음료","cat_mid":"공통","cat_small":"에이드"},{"store":"다산","item":"시트러스 주스","qty":266,"net":1995000,"cat_big":"음료","cat_mid":"공통","cat_small":"주스"},{"store":"다산","item":"문경 사과 주스","qty":415,"net":3112500,"cat_big":"음료","cat_mid":"공통","cat_small":"주스"},{"store":"다산","item":"초코 라떼","qty":99,"net":673200,"cat_big":"음료","cat_mid":"공통","cat_small":"논커피"},{"store":"다산","item":"I 초코 라떼","qty":355,"net":2414000,"cat_big":"음료","cat_mid":"공통","cat_small":"논커피"},{"store":"다산","item":"제주 말차 라떼","qty":188,"net":1278400,"cat_big":"음료","cat_mid":"공통","cat_small":"논커피"},{"store":"다산","item":"I 제주 말차 라떼","qty":404,"net":2747200,"cat_big":"음료","cat_mid":"공통","cat_small":"논커피"},{"store":"다산","item":"밀크티","qty":107,"net":727600,"cat_big":"음료","cat_mid":"공통","cat_small":"논커피"},{"store":"다산","item":"I 밀크티","qty":203,"net":1380400,"cat_big":"음료","cat_mid":"공통","cat_small":"논커피"},{"store":"다산","item":"세러니티","qty":311,"net":1803800,"cat_big":"음료","cat_mid":"공통","cat_small":"차"},{"store":"다산","item":"I 세러니티","qty":96,"net":556800,"cat_big":"음료","cat_mid":"공통","cat_small":"차"},{"store":"다산","item":"크림슨펀치","qty":137,"net":794600,"cat_big":"음료","cat_mid":"공통","cat_small":"차"},{"store":"다산","item":"I 크림슨펀치","qty":96,"net":556800,"cat_big":"음료","cat_mid":"공통","cat_small":"차"},{"store":"다산","item":"I 겐마이차","qty":52,"net":301600,"cat_big":"음료","cat_mid":"공통","cat_small":"차"},{"store":"다산","item":"얼그레이","qty":81,"net":469800,"cat_big":"음료","cat_mid":"공통","cat_small":"차"},{"store":"다산","item":"I 피치우롱","qty":155,"net":899000,"cat_big":"음료","cat_mid":"공통","cat_small":"차"},{"store":"다산","item":"베이비치노(코코아)","qty":95,"net":456000,"cat_big":"음료","cat_mid":"스페셜","cat_small":"키즈"},{"store":"다산","item":"I 베이비치노(코코아)","qty":64,"net":307200,"cat_big":"음료","cat_mid":"스페셜","cat_small":"키즈"},{"store":"다산","item":"H 애플 시나몬 세러니티","qty":139,"net":903500,"cat_big":"음료","cat_mid":"스페셜","cat_small":"시즌음료"},{"store":"다산","item":"I 애플 시나몬 세러니티","qty":139,"net":903500,"cat_big":"음료","cat_mid":"스페셜","cat_small":"시즌음료"},{"store":"다산","item":"얼그레이 그린플럼티","qty":214,"net":1391000,"cat_big":"음료","cat_mid":"스페셜","cat_small":"시즌음료"},{"store":"다산","item":"럼 마론 크림 라떼","qty":158,"net":1264000,"cat_big":"음료","cat_mid":"스페셜","cat_small":"시즌음료"},{"store":"다산","item":"콘 크러쉬 블렌디드","qty":136,"net":788800,"cat_big":"음료","cat_mid":"공통","cat_small":"블랜디드"},{"store":"다산","item":"애플 시나몬 크럼블 아이스크림 추가","qty":117,"net":117000,"cat_big":"음료","cat_mid":"스페셜","cat_small":"시즌음료"},{"store":"다산","item":"레몬 마들렌","qty":90,"net":342000,"cat_big":"베이커리","cat_mid":"구움과자","cat_small":"마들렌"},{"store":"다산","item":"버터 사블레","qty":41,"net":114800,"cat_big":"베이커리","cat_mid":"구움과자","cat_small":"사블레"},{"store":"다산","item":"바닐라 사블레","qty":27,"net":75600,"cat_big":"베이커리","cat_mid":"구움과자","cat_small":"사블레"},{"store":"다산","item":"화이트 마차 사블레","qty":37,"net":103600,"cat_big":"베이커리","cat_mid":"구움과자","cat_small":"사블레"},{"store":"다산","item":"솔티드 초콜릿 사블레","qty":41,"net":114800,"cat_big":"베이커리","cat_mid":"구움과자","cat_small":"사블레"},{"store":"다산","item":"플레인 버터 스콘","qty":116,"net":556800,"cat_big":"베이커리","cat_mid":"구움과자","cat_small":"스콘"},{"store":"다산","item":"레몬 블루베리 스콘","qty":92,"net":460000,"cat_big":"베이커리","cat_mid":"구움과자","cat_small":"스콘"},{"store":"다산","item":"크렌베리 화이트 초콜릿 스콘","qty":110,"net":572000,"cat_big":"베이커리","cat_mid":"구움과자","cat_small":"스콘"},{"store":"다산","item":"애플잼 스콘","qty":423,"net":2115000,"cat_big":"베이커리","cat_mid":"구움과자","cat_small":"스콘"},{"store":"다산","item":"더블 초콜릿 쿠키","qty":64,"net":268800,"cat_big":"베이커리","cat_mid":"구움과자","cat_small":"쿠키"},{"store":"다산","item":"크랜베리 아몬드 쿠키N","qty":35,"net":133000,"cat_big":"베이커리","cat_mid":"구움과자","cat_small":"쿠키"},{"store":"다산","item":"레몬 파운드","qty":234,"net":1053000,"cat_big":"베이커리","cat_mid":"구움과자","cat_small":"파운드"},{"store":"다산","item":"소금 초콜릿 휘낭시에","qty":92,"net":368000,"cat_big":"베이커리","cat_mid":"구움과자","cat_small":"휘낭시에"},{"store":"다산","item":"무화과 크림 치즈 휘낭시에","qty":93,"net":353400,"cat_big":"베이커리","cat_mid":"구움과자","cat_small":"휘낭시에"},{"store":"다산","item":"애플 시나몬 크럼블","qty":246,"net":1353000,"cat_big":"베이커리","cat_mid":"구움과자","cat_small":"크럼블"},{"store":"다산","item":"플레인 사워도우","qty":84,"net":672000,"cat_big":"베이커리","cat_mid":"브레드","cat_small":"건강빵"},{"store":"다산","item":"단호박 크림 치즈 깜파뉴","qty":203,"net":1319500,"cat_big":"베이커리","cat_mid":"브레드","cat_small":"건강빵"},{"store":"다산","item":"프렌치 바게트","qty":31,"net":124000,"cat_big":"베이커리","cat_mid":"브레드","cat_small":"건강빵"},{"store":"다산","item":"단호박 치아바타","qty":235,"net":1057500,"cat_big":"베이커리","cat_mid":"브레드","cat_small":"건강빵"},{"store":"다산","item":"먹물 롤 치즈 치아바타","qty":230,"net":966000,"cat_big":"베이커리","cat_mid":"브레드","cat_small":"건강빵"},{"store":"다산","item":"올리브 치즈 치아바타","qty":244,"net":1098000,"cat_big":"베이커리","cat_mid":"브레드","cat_small":"건강빵"},{"store":"다산","item":"페퍼로니 에멘탈 치즈 깜파뉴","qty":171,"net":1162800,"cat_big":"베이커리","cat_mid":"브레드","cat_small":"건강빵"},{"store":"다산","item":"고르곤졸라 깜파뉴","qty":171,"net":1162800,"cat_big":"베이커리","cat_mid":"브레드","cat_small":"건강빵"},{"store":"다산","item":"무화과 샤워도우","qty":91,"net":728000,"cat_big":"베이커리","cat_mid":"브레드","cat_small":"건강빵"},{"store":"다산","item":"미니 무화과 샤워도우","qty":262,"net":995600,"cat_big":"베이커리","cat_mid":"브레드","cat_small":"건강빵"},{"store":"다산","item":"플레인 베이글","qty":142,"net":568000,"cat_big":"베이커리","cat_mid":"브레드","cat_small":"베이글"},{"store":"다산","item":"더블 베리 베이글","qty":151,"net":724800,"cat_big":"베이커리","cat_mid":"브레드","cat_small":"베이글"},{"store":"다산","item":"라우겐 베이글","qty":184,"net":828000,"cat_big":"베이커리","cat_mid":"브레드","cat_small":"베이글"},{"store":"다산","item":"어니언 베이글","qty":113,"net":508500,"cat_big":"베이커리","cat_mid":"브레드","cat_small":"베이글"},{"store":"다산","item":"페퍼로니 할라피뇨 베이글","qty":201,"net":1045200,"cat_big":"베이커리","cat_mid":"브레드","cat_small":"베이글"},{"store":"다산","item":"치즈 포테이토 베이글","qty":225,"net":1350000,"cat_big":"베이커리","cat_mid":"브레드","cat_small":"베이글"},{"store":"다산","item":"버터 라우겐 베이글","qty":320,"net":1984000,"cat_big":"베이커리","cat_mid":"브레드","cat_small":"베이글"},{"store":"다산","item":"어니언 크림 치즈 베이글","qty":249,"net":1792800,"cat_big":"베이커리","cat_mid":"브레드","cat_small":"베이글"},{"store":"다산","item":"쪽파 크림 치즈 베이글","qty":199,"net":1492500,"cat_big":"베이커리","cat_mid":"브레드","cat_small":"베이글"},{"store":"다산","item":"갈릭 베이글","qty":264,"net":1267200,"cat_big":"베이커리","cat_mid":"브레드","cat_small":"베이글"},{"store":"다산","item":"얼 그레이 무화과 베이글","qty":165,"net":742500,"cat_big":"베이커리","cat_mid":"브레드","cat_small":"베이글"},{"store":"다산","item":"올리브 베이글","qty":284,"net":1192800,"cat_big":"베이커리","cat_mid":"브레드","cat_small":"베이글"},{"store":"다산","item":"모카 베이글","qty":290,"net":1508000,"cat_big":"베이커리","cat_mid":"브레드","cat_small":"베이글"},{"store":"다산","item":"플레인 소금빵","qty":1033,"net":4338600,"cat_big":"베이커리","cat_mid":"브레드","cat_small":"소금빵"},{"store":"다산","item":"갈릭 소금빵","qty":252,"net":1209600,"cat_big":"베이커리","cat_mid":"브레드","cat_small":"소금빵"},{"store":"다산","item":"우유 크림 소금빵","qty":490,"net":2450000,"cat_big":"베이커리","cat_mid":"브레드","cat_small":"소금빵"},{"store":"다산","item":"앙버터 소금빵","qty":439,"net":2282800,"cat_big":"베이커리","cat_mid":"브레드","cat_small":"소금빵"},{"store":"다산","item":"명란 소금빵","qty":397,"net":1905600,"cat_big":"베이커리","cat_mid":"브레드","cat_small":"소금빵"},{"store":"다산","item":"우유 크림 치즈 소금빵","qty":370,"net":1850000,"cat_big":"베이커리","cat_mid":"브레드","cat_small":"소금빵"},{"store":"다산","item":"카스텔라 소금빵","qty":230,"net":1196000,"cat_big":"베이커리","cat_mid":"브레드","cat_small":"소금빵"},{"store":"다산","item":"수제 단팥빵","qty":327,"net":1242600,"cat_big":"베이커리","cat_mid":"브레드","cat_small":"일반빵"},{"store":"다산","item":"소보로빵","qty":199,"net":756200,"cat_big":"베이커리","cat_mid":"브레드","cat_small":"일반빵"},{"store":"다산","item":"우유 식빵","qty":61,"net":378200,"cat_big":"베이커리","cat_mid":"브레드","cat_small":"일반빵"},{"store":"다산","item":"밤 식빵","qty":181,"net":1267000,"cat_big":"베이커리","cat_mid":"브레드","cat_small":"일반빵"},{"store":"다산","item":"팥 식빵","qty":84,"net":520800,"cat_big":"베이커리","cat_mid":"브레드","cat_small":"일반빵"},{"store":"다산","item":"버터 크림 브레드","qty":168,"net":588000,"cat_big":"베이커리","cat_mid":"브레드","cat_small":"일반빵"},{"store":"다산","item":"커스타드 브레드","qty":163,"net":570500,"cat_big":"베이커리","cat_mid":"브레드","cat_small":"일반빵"},{"store":"다산","item":"본마망 딸기잼30g","qty":15,"net":30000,"cat_big":"베이커리","cat_mid":"스프레드/잼/오일","cat_small":"잼"},{"store":"다산","item":"올리브 오일 발사믹","qty":76,"net":114000,"cat_big":"베이커리","cat_mid":"스프레드/잼/오일","cat_small":"오일"},{"store":"다산","item":"카라멜 바스크","qty":53,"net":636000,"cat_big":"베이커리","cat_mid":"케이크","cat_small":"그 외 케이크"},{"store":"다산","item":"딸기 초콜릿 롤 케이크(조각)","qty":123,"net":922500,"cat_big":"베이커리","cat_mid":"케이크","cat_small":"조각 케이크"},{"store":"다산","item":"리얼 애플망고 케이크(조각)","qty":275,"net":2612500,"cat_big":"베이커리","cat_mid":"케이크","cat_small":"조각 케이크"},{"store":"다산","item":"뉴욕 치즈 케이크(조각)","qty":208,"net":1768000,"cat_big":"베이커리","cat_mid":"케이크","cat_small":"조각 케이크"},{"store":"다산","item":"무화과 생크림 케이크 (조각)","qty":237,"net":2251500,"cat_big":"베이커리","cat_mid":"케이크","cat_small":"조각 케이크"},{"store":"다산","item":"몽블랑 (조각)","qty":155,"net":1472500,"cat_big":"베이커리","cat_mid":"케이크","cat_small":"조각 케이크"},{"store":"다산","item":"리얼 애플망고 케이크(1호)","qty":25,"net":1050000,"cat_big":"베이커리","cat_mid":"케이크","cat_small":"홀 케이크"},{"store":"다산","item":"무화과 생크림 케이크 (1호)","qty":21,"net":903000,"cat_big":"베이커리","cat_mid":"케이크","cat_small":"홀 케이크"},{"store":"다산","item":"몽블랑 (1호)","qty":18,"net":810000,"cat_big":"베이커리","cat_mid":"케이크","cat_small":"홀 케이크"},{"store":"다산","item":"블루베리 데니쉬","qty":176,"net":1267200,"cat_big":"베이커리","cat_mid":"페이스트리","cat_small":"데니쉬"},{"store":"다산","item":"얼 그레이 무화과 데니쉬","qty":160,"net":1200000,"cat_big":"베이커리","cat_mid":"페이스트리","cat_small":"데니쉬"},{"store":"다산","item":"썸머 후르츠 데니쉬","qty":183,"net":1372500,"cat_big":"베이커리","cat_mid":"페이스트리","cat_small":"데니쉬"},{"store":"다산","item":"플레인 퀸 아망","qty":248,"net":1190400,"cat_big":"베이커리","cat_mid":"페이스트리","cat_small":"퀸 아망"},{"store":"다산","item":"얼 그레이 퀸 아망","qty":80,"net":440000,"cat_big":"베이커리","cat_mid":"페이스트리","cat_small":"퀸 아망"},{"store":"다산","item":"두바이 퀸 아망","qty":216,"net":1252800,"cat_big":"베이커리","cat_mid":"페이스트리","cat_small":"퀸 아망"},{"store":"다산","item":"플레인 크루아상","qty":219,"net":985500,"cat_big":"베이커리","cat_mid":"페이스트리","cat_small":"크루아상 계열"},{"store":"다산","item":"뺑 오 쇼콜라","qty":391,"net":2033200,"cat_big":"베이커리","cat_mid":"페이스트리","cat_small":"크루아상 계열"},{"store":"다산","item":"뉴욕 페이스트리","qty":321,"net":1765500,"cat_big":"베이커리","cat_mid":"페이스트리","cat_small":"크루아상 계열"},{"store":"다산","item":"스리라차 소시지 페이스트리","qty":437,"net":2709400,"cat_big":"베이커리","cat_mid":"페이스트리","cat_small":"크루아상 계열"},{"store":"다산","item":"몽블랑 데니쉬","qty":331,"net":2052200,"cat_big":"베이커리","cat_mid":"페이스트리","cat_small":"데니쉬"},{"store":"다산","item":"뺑 오 우바 화이트 쇼콜라","qty":118,"net":684400,"cat_big":"베이커리","cat_mid":"페이스트리","cat_small":"크루아상 계열"},{"store":"다산","item":"딸기 커스터드 턴오버","qty":227,"net":1316600,"cat_big":"베이커리","cat_mid":"페이스트리","cat_small":"크루아상 계열"},{"store":"다산","item":"아몬드 크루아상","qty":291,"net":1396800,"cat_big":"베이커리","cat_mid":"페이스트리","cat_small":"크루아상 계열"},{"store":"다산","item":"애플 턴오버","qty":237,"net":1540500,"cat_big":"베이커리","cat_mid":"페이스트리","cat_small":"크루아상 계열"},{"store":"다산","item":"초콜릿 파이 프레첼","qty":162,"net":842400,"cat_big":"베이커리","cat_mid":"페이스트리","cat_small":"크루아상 계열"},{"store":"다산","item":"초콜릿 크룽지","qty":206,"net":988800,"cat_big":"베이커리","cat_mid":"페이스트리","cat_small":"크루아상 계열"},{"store":"다산","item":"시나몬 크룽지","qty":167,"net":751500,"cat_big":"베이커리","cat_mid":"페이스트리","cat_small":"크루아상 계열"},{"store":"다산","item":"캐러멜 넛츠 크림 페이스트리","qty":142,"net":852000,"cat_big":"베이커리","cat_mid":"페이스트리","cat_small":"크루아상 계열"},{"store":"다산","item":"블루베리 크림 브레드","qty":207,"net":1552500,"cat_big":"베이커리","cat_mid":"페이스트리","cat_small":"크루아상 계열"},{"store":"다산","item":"MiNi)머쉬룸 수프","qty":118,"net":354000,"cat_big":"푸드","cat_mid":"다산 푸드","cat_small":"샐러드/스프"},{"store":"다산","item":"INC)비프 샐러드","qty":152,"net":2432000,"cat_big":"푸드","cat_mid":"다산 푸드","cat_small":"샐러드/스프"},{"store":"다산","item":"시저 샐러드","qty":90,"net":1170000,"cat_big":"푸드","cat_mid":"다산 푸드","cat_small":"샐러드/스프"},{"store":"다산","item":"INC)브런치 플레이트","qty":142,"net":2414000,"cat_big":"푸드","cat_mid":"다산 푸드","cat_small":"브런치"},{"store":"다산","item":"INC)멜티드 샌드위치","qty":144,"net":2304000,"cat_big":"푸드","cat_mid":"다산 푸드","cat_small":"브런치"},{"store":"다산","item":"감자튀김","qty":62,"net":186000,"cat_big":"푸드","cat_mid":"다산 푸드","cat_small":"브런치"},{"store":"다산","item":"INC)초리조 파스타","qty":109,"net":1853000,"cat_big":"푸드","cat_mid":"다산 푸드","cat_small":"파스타"},{"store":"다산","item":"INC)봉골레 파스타","qty":95,"net":1615000,"cat_big":"푸드","cat_mid":"다산 푸드","cat_small":"파스타"},{"store":"다산","item":"INC)크림 파스타","qty":136,"net":2176000,"cat_big":"푸드","cat_mid":"다산 푸드","cat_small":"파스타"},{"store":"다산","item":"INC)라구 파스타","qty":144,"net":2304000,"cat_big":"푸드","cat_mid":"다산 푸드","cat_small":"파스타"},{"store":"다산","item":"ETH 예가체프 코케허니G1(N)200g","qty":18,"net":333000,"cat_big":"MD/기타","cat_mid":"MD","cat_small":"커피류"},{"store":"다산","item":"I 얼그레이","qty":41,"net":237800,"cat_big":"음료","cat_mid":"공통","cat_small":"차"},{"store":"다산","item":"오네로소","qty":32,"net":198400,"cat_big":"음료","cat_mid":"스페셜","cat_small":"에쏘바"},{"store":"수원","item":"자카파 밀크","qty":520,"net":4160000,"cat_big":"음료","cat_mid":"공통","cat_small":"시그니처"},{"store":"수원","item":"만원(수원점)","qty":519,"net":5190000,"cat_big":"음료","cat_mid":"음료","cat_small":"스타필드 수원점"},{"store":"수원","item":"천원(수원점)","qty":172,"net":172000,"cat_big":"음료","cat_mid":"음료","cat_small":"스타필드 수원점"},{"store":"수원","item":"백원(수원점)","qty":118,"net":11800,"cat_big":"음료","cat_mid":"음료","cat_small":"스타필드 수원점"},{"store":"수원","item":"유기농 우유 125ML","qty":64,"net":128000,"cat_big":"RTD","cat_mid":"음료","cat_small":"RTD음료"},{"store":"수원","item":"유기농 초코우유 125ML","qty":73,"net":146000,"cat_big":"RTD","cat_mid":"음료","cat_small":"RTD음료"},{"store":"수원","item":"아메리카노(R)","qty":123,"net":836400,"cat_big":"음료","cat_mid":"공통","cat_small":"시그니처"},{"store":"수원","item":"I 아메리카노(R)","qty":702,"net":4773600,"cat_big":"음료","cat_mid":"공통","cat_small":"시그니처"},{"store":"수원","item":"카페라떼(R)","qty":98,"net":666400,"cat_big":"음료","cat_mid":"공통","cat_small":"시그니처"},{"store":"수원","item":"I 카페라떼(R)","qty":247,"net":1679600,"cat_big":"음료","cat_mid":"공통","cat_small":"시그니처"},{"store":"수원","item":"H 에티오피아 코케허니","qty":56,"net":364000,"cat_big":"음료","cat_mid":"공통","cat_small":"드립커피"},{"store":"수원","item":"I 에티오피아 코케허니","qty":117,"net":760500,"cat_big":"음료","cat_mid":"공통","cat_small":"드립커피"},{"store":"수원","item":"에스프레소(DARK)","qty":27,"net":145800,"cat_big":"음료","cat_mid":"공통","cat_small":"커피"},{"store":"수원","item":"아메리카노(D)","qty":195,"net":1053000,"cat_big":"음료","cat_mid":"공통","cat_small":"커피"},{"store":"수원","item":"아메리카노(INC)","qty":363,"net":1960200,"cat_big":"음료","cat_mid":"공통","cat_small":"커피"},{"store":"수원","item":"아메리카노(DARK)","qty":537,"net":2899800,"cat_big":"음료","cat_mid":"공통","cat_small":"커피"},{"store":"수원","item":"I 아메리카노(D)","qty":670,"net":3618000,"cat_big":"음료","cat_mid":"공통","cat_small":"커피"},{"store":"수원","item":"I 아메리카노(INC)","qty":1538,"net":8305200,"cat_big":"음료","cat_mid":"공통","cat_small":"커피"},{"store":"수원","item":"I 아메리카노(DARK)","qty":2774,"net":14979600,"cat_big":"음료","cat_mid":"공통","cat_small":"커피"},{"store":"수원","item":"아메리카노_UP(INC)","qty":133,"net":784700,"cat_big":"음료","cat_mid":"공통","cat_small":"커피"},{"store":"수원","item":"아메리카노_UP(DARK)","qty":220,"net":1298000,"cat_big":"음료","cat_mid":"공통","cat_small":"커피"},{"store":"수원","item":"플랫 화이트","qty":147,"net":852600,"cat_big":"음료","cat_mid":"공통","cat_small":"커피"},{"store":"수원","item":"I 플랫 화이트","qty":168,"net":974400,"cat_big":"음료","cat_mid":"공통","cat_small":"커피"},{"store":"수원","item":"카페 라떼","qty":616,"net":3572800,"cat_big":"음료","cat_mid":"공통","cat_small":"커피"},{"store":"수원","item":"I 카페 라떼","qty":1069,"net":6200200,"cat_big":"음료","cat_mid":"공통","cat_small":"커피"},{"store":"수원","item":"I 연유 라떼","qty":216,"net":1404000,"cat_big":"음료","cat_mid":"공통","cat_small":"커피"},{"store":"수원","item":"바닐라빈 라떼","qty":147,"net":955500,"cat_big":"음료","cat_mid":"공통","cat_small":"커피"},{"store":"수원","item":"I 바닐라빈 라떼","qty":750,"net":4875000,"cat_big":"음료","cat_mid":"공통","cat_small":"커피"},{"store":"수원","item":"쿠키앤크림 블렌디드","qty":183,"net":1372500,"cat_big":"음료","cat_mid":"공통","cat_small":"블랜디드"},{"store":"수원","item":"제주 한라봉 블랜디드","qty":360,"net":2700000,"cat_big":"음료","cat_mid":"공통","cat_small":"블랜디드"},{"store":"수원","item":"자몽 에이드","qty":246,"net":1845000,"cat_big":"음료","cat_mid":"공통","cat_small":"에이드"},{"store":"수원","item":"청포도 라임 에이드","qty":304,"net":2280000,"cat_big":"음료","cat_mid":"공통","cat_small":"에이드"},{"store":"수원","item":"시트러스 주스","qty":201,"net":1507500,"cat_big":"음료","cat_mid":"공통","cat_small":"주스"},{"store":"수원","item":"문경 사과 주스","qty":312,"net":2340000,"cat_big":"음료","cat_mid":"공통","cat_small":"주스"},{"store":"수원","item":"초코 라떼","qty":57,"net":387600,"cat_big":"음료","cat_mid":"공통","cat_small":"논커피"},{"store":"수원","item":"I 초코 라떼","qty":360,"net":2448000,"cat_big":"음료","cat_mid":"공통","cat_small":"논커피"},{"store":"수원","item":"제주 말차 라떼","qty":78,"net":530400,"cat_big":"음료","cat_mid":"공통","cat_small":"논커피"},{"store":"수원","item":"I 제주 말차 라떼","qty":357,"net":2427600,"cat_big":"음료","cat_mid":"공통","cat_small":"논커피"},{"store":"수원","item":"I 밀크티","qty":136,"net":924800,"cat_big":"음료","cat_mid":"공통","cat_small":"논커피"},{"store":"수원","item":"세러니티","qty":87,"net":504600,"cat_big":"음료","cat_mid":"공통","cat_small":"차"},{"store":"수원","item":"I 세러니티","qty":69,"net":400200,"cat_big":"음료","cat_mid":"공통","cat_small":"차"},{"store":"수원","item":"크림슨펀치","qty":42,"net":243600,"cat_big":"음료","cat_mid":"공통","cat_small":"차"},{"store":"수원","item":"얼그레이","qty":39,"net":226200,"cat_big":"음료","cat_mid":"공통","cat_small":"차"},{"store":"수원","item":"피치우롱","qty":48,"net":278400,"cat_big":"음료","cat_mid":"공통","cat_small":"차"},{"store":"수원","item":"I 피치우롱","qty":126,"net":730800,"cat_big":"음료","cat_mid":"공통","cat_small":"차"},{"store":"수원","item":"I 애플 시나몬 세러니티","qty":94,"net":611000,"cat_big":"음료","cat_mid":"스페셜","cat_small":"시즌음료"},{"store":"수원","item":"얼그레이 그린플럼티","qty":129,"net":838500,"cat_big":"음료","cat_mid":"스페셜","cat_small":"시즌음료"},{"store":"수원","item":"럼 마론 크림 라떼","qty":404,"net":3232000,"cat_big":"음료","cat_mid":"스페셜","cat_small":"시즌음료"},{"store":"수원","item":"애플 시나몬 크럼블 아이스크림 추가","qty":133,"net":133000,"cat_big":"음료","cat_mid":"스페셜","cat_small":"시즌음료"},{"store":"수원","item":"레몬 마들렌","qty":87,"net":330600,"cat_big":"베이커리","cat_mid":"구움과자","cat_small":"마들렌"},{"store":"수원","item":"플레인 버터 스콘","qty":94,"net":451200,"cat_big":"베이커리","cat_mid":"구움과자","cat_small":"스콘"},{"store":"수원","item":"애플잼 스콘","qty":255,"net":1275000,"cat_big":"베이커리","cat_mid":"구움과자","cat_small":"스콘"},{"store":"수원","item":"레몬 파운드","qty":125,"net":562500,"cat_big":"베이커리","cat_mid":"구움과자","cat_small":"파운드"},{"store":"수원","item":"얼 그레이 파운드","qty":112,"net":504000,"cat_big":"베이커리","cat_mid":"구움과자","cat_small":"파운드"},{"store":"수원","item":"플레인 휘낭시에","qty":84,"net":319200,"cat_big":"베이커리","cat_mid":"구움과자","cat_small":"휘낭시에"},{"store":"수원","item":"소금 초콜릿 휘낭시에","qty":64,"net":256000,"cat_big":"베이커리","cat_mid":"구움과자","cat_small":"휘낭시에"},{"store":"수원","item":"무화과 크림 치즈 휘낭시에","qty":61,"net":231800,"cat_big":"베이커리","cat_mid":"구움과자","cat_small":"휘낭시에"},{"store":"수원","item":"애플 시나몬 크럼블","qty":602,"net":3311000,"cat_big":"베이커리","cat_mid":"구움과자","cat_small":"크럼블"},{"store":"수원","item":"무화과 샤워도우","qty":64,"net":512000,"cat_big":"베이커리","cat_mid":"브레드","cat_small":"건강빵"},{"store":"수원","item":"미니 무화과 샤워도우","qty":206,"net":782800,"cat_big":"베이커리","cat_mid":"브레드","cat_small":"건강빵"},{"store":"수원","item":"플레인 소금빵","qty":537,"net":2255400,"cat_big":"베이커리","cat_mid":"브레드","cat_small":"소금빵"},{"store":"수원","item":"갈릭 소금빵","qty":157,"net":753600,"cat_big":"베이커리","cat_mid":"브레드","cat_small":"소금빵"},{"store":"수원","item":"우유 크림 소금빵","qty":415,"net":2075000,"cat_big":"베이커리","cat_mid":"브레드","cat_small":"소금빵"},{"store":"수원","item":"명란 소금빵","qty":164,"net":787200,"cat_big":"베이커리","cat_mid":"브레드","cat_small":"소금빵"},{"store":"수원","item":"인크 로쉐","qty":276,"net":1600800,"cat_big":"베이커리","cat_mid":"브레드","cat_small":"일반빵"},{"store":"수원","item":"플레인 퀸 아망","qty":197,"net":945600,"cat_big":"베이커리","cat_mid":"페이스트리","cat_small":"퀸 아망"},{"store":"수원","item":"초콜릿 퀸 아망","qty":155,"net":806000,"cat_big":"베이커리","cat_mid":"페이스트리","cat_small":"퀸 아망"},{"store":"수원","item":"두바이 퀸 아망","qty":184,"net":1067200,"cat_big":"베이커리","cat_mid":"페이스트리","cat_small":"퀸 아망"},{"store":"하남","item":"유기농 주스(티라노니)","qty":19,"net":47500,"cat_big":"RTD","cat_mid":"음료","cat_small":"RTD음료"},{"store":"하남","item":"그라운드 에티오피아(15T)","qty":1,"net":25000,"cat_big":"MD/기타","cat_mid":"MD","cat_small":"커피류"},{"store":"하남","item":"그라운드 타이거즈(15T)","qty":3,"net":75000,"cat_big":"MD/기타","cat_mid":"MD","cat_small":"커피류"},{"store":"하남","item":"다크 오리진블렌드 200g","qty":6,"net":96000,"cat_big":"MD/기타","cat_mid":"MD","cat_small":"커피류"},{"store":"하남","item":"쇼핑백(NEW오렌지)","qty":3,"net":3000,"cat_big":"MD/기타","cat_mid":"MD","cat_small":"포장"},{"store":"하남","item":"크라프트 쇼핑백","qty":25,"net":5000,"cat_big":"MD/기타","cat_mid":"MD","cat_small":"포장"},{"store":"하남","item":"자카파_밀크","qty":73,"net":584000,"cat_big":"음료","cat_mid":"공통","cat_small":"시그니처"},{"store":"하남","item":"I 엘살바도르 파카마라 내추럴","qty":13,"net":84500,"cat_big":"음료","cat_mid":"공통","cat_small":"드립커피"},{"store":"하남","item":"H 에티오피아 코케허니","qty":61,"net":396500,"cat_big":"음료","cat_mid":"공통","cat_small":"드립커피"},{"store":"하남","item":"에스프레소(INC)","qty":6,"net":32400,"cat_big":"음료","cat_mid":"공통","cat_small":"커피"},{"store":"하남","item":"아메리카노(D)","qty":77,"net":415800,"cat_big":"음료","cat_mid":"공통","cat_small":"커피"},{"store":"하남","item":"아메리카노(INC)","qty":240,"net":1296000,"cat_big":"음료","cat_mid":"공통","cat_small":"커피"},{"store":"하남","item":"아메리카노(DARK)","qty":200,"net":1080000,"cat_big":"음료","cat_mid":"공통","cat_small":"커피"},{"store":"하남","item":"I 아메리카노(D)","qty":135,"net":729000,"cat_big":"음료","cat_mid":"공통","cat_small":"커피"},{"store":"하남","item":"I 아메리카노(INC)","qty":356,"net":1922400,"cat_big":"음료","cat_mid":"공통","cat_small":"커피"},{"store":"하남","item":"I 아메리카노(DARK)","qty":417,"net":2251800,"cat_big":"음료","cat_mid":"공통","cat_small":"커피"},{"store":"하남","item":"아메리카노_UP(INC)","qty":5,"net":29500,"cat_big":"음료","cat_mid":"공통","cat_small":"커피"},{"store":"하남","item":"아메리카노_UP(DARK)","qty":7,"net":41300,"cat_big":"음료","cat_mid":"공통","cat_small":"커피"},{"store":"하남","item":"I 아메리카노_UP(DARK)","qty":51,"net":300900,"cat_big":"음료","cat_mid":"공통","cat_small":"커피"},{"store":"하남","item":"+샷 추가","qty":22,"net":11000,"cat_big":"음료","cat_mid":"공통","cat_small":"커피"},{"store":"하남","item":"카페 라떼","qty":278,"net":1612400,"cat_big":"음료","cat_mid":"공통","cat_small":"커피"},{"store":"하남","item":"I 카페 라떼","qty":209,"net":1212200,"cat_big":"음료","cat_mid":"공통","cat_small":"커피"},{"store":"하남","item":"I 연유 라떼","qty":26,"net":169000,"cat_big":"음료","cat_mid":"공통","cat_small":"커피"},{"store":"하남","item":"바닐라빈 라떼","qty":41,"net":266500,"cat_big":"음료","cat_mid":"공통","cat_small":"커피"},{"store":"하남","item":"I 바닐라빈 라떼","qty":102,"net":663000,"cat_big":"음료","cat_mid":"공통","cat_small":"커피"},{"store":"하남","item":"I 카라멜 마끼아또","qty":14,"net":91000,"cat_big":"음료","cat_mid":"공통","cat_small":"커피"},{"store":"하남","item":"쿠키앤크림 블렌디드","qty":14,"net":105000,"cat_big":"음료","cat_mid":"공통","cat_small":"블랜디드"},{"store":"하남","item":"제주 한라봉 블랜디드","qty":25,"net":187500,"cat_big":"음료","cat_mid":"공통","cat_small":"블랜디드"},{"store":"하남","item":"시트러스 주스","qty":27,"net":202500,"cat_big":"음료","cat_mid":"공통","cat_small":"주스"},{"store":"하남","item":"문경 사과 주스","qty":53,"net":397500,"cat_big":"음료","cat_mid":"공통","cat_small":"주스"},{"store":"하남","item":"I 초코 라떼","qty":24,"net":163200,"cat_big":"음료","cat_mid":"공통","cat_small":"논커피"},{"store":"하남","item":"밀크티","qty":9,"net":61200,"cat_big":"음료","cat_mid":"공통","cat_small":"논커피"},{"store":"하남","item":"I 밀크티","qty":23,"net":156400,"cat_big":"음료","cat_mid":"공통","cat_small":"논커피"},{"store":"하남","item":"밀크 아이스크림","qty":41,"net":196800,"cat_big":"음료","cat_mid":"공통","cat_small":"논커피"},{"store":"하남","item":"세러니티","qty":61,"net":353800,"cat_big":"음료","cat_mid":"공통","cat_small":"차"},{"store":"하남","item":"I 크림슨펀치","qty":17,"net":98600,"cat_big":"음료","cat_mid":"공통","cat_small":"차"},{"store":"하남","item":"I 얼그레이","qty":8,"net":46400,"cat_big":"음료","cat_mid":"공통","cat_small":"차"},{"store":"하남","item":"I 애플 시나몬 세러니티","qty":19,"net":123500,"cat_big":"음료","cat_mid":"스페셜","cat_small":"시즌음료"},{"store":"하남","item":"럼 마론 크림 라떼","qty":31,"net":248000,"cat_big":"음료","cat_mid":"스페셜","cat_small":"시즌음료"},{"store":"하남","item":"콘 크러쉬 블렌디드","qty":23,"net":133400,"cat_big":"음료","cat_mid":"공통","cat_small":"블랜디드"},{"store":"하남","item":"레몬 마들렌","qty":53,"net":201400,"cat_big":"베이커리","cat_mid":"구움과자","cat_small":"마들렌"},{"store":"하남","item":"크렌베리 화이트 초콜릿 스콘","qty":8,"net":41600,"cat_big":"베이커리","cat_mid":"구움과자","cat_small":"스콘"},{"store":"하남","item":"애플잼 스콘","qty":60,"net":300000,"cat_big":"베이커리","cat_mid":"구움과자","cat_small":"스콘"},{"store":"하남","item":"더블 초콜릿 쿠키","qty":23,"net":96600,"cat_big":"베이커리","cat_mid":"구움과자","cat_small":"쿠키"},{"store":"하남","item":"얼 그레이 파운드","qty":35,"net":157500,"cat_big":"베이커리","cat_mid":"구움과자","cat_small":"파운드"},{"store":"하남","item":"플레인 휘낭시에","qty":53,"net":201400,"cat_big":"베이커리","cat_mid":"구움과자","cat_small":"휘낭시에"},{"store":"하남","item":"소금 초콜릿 휘낭시에","qty":42,"net":168000,"cat_big":"베이커리","cat_mid":"구움과자","cat_small":"휘낭시에"},{"store":"하남","item":"애플 시나몬 크럼블","qty":58,"net":319000,"cat_big":"베이커리","cat_mid":"구움과자","cat_small":"크럼블"},{"store":"하남","item":"미니 무화과 샤워도우","qty":105,"net":399000,"cat_big":"베이커리","cat_mid":"브레드","cat_small":"건강빵"},{"store":"하남","item":"라우겐 베이글","qty":42,"net":189000,"cat_big":"베이커리","cat_mid":"브레드","cat_small":"베이글"},{"store":"하남","item":"버터 라우겐 베이글","qty":54,"net":334800,"cat_big":"베이커리","cat_mid":"브레드","cat_small":"베이글"},{"store":"하남","item":"잠봉 뵈르 소금빵","qty":44,"net":286000,"cat_big":"베이커리","cat_mid":"브레드","cat_small":"샌드위치"},{"store":"하남","item":"에그 샐러드 소금빵","qty":48,"net":278400,"cat_big":"베이커리","cat_mid":"브레드","cat_small":"샌드위치"},{"store":"하남","item":"플레인 소금빵","qty":140,"net":588000,"cat_big":"베이커리","cat_mid":"브레드","cat_small":"소금빵"},{"store":"하남","item":"수제 단팥빵","qty":78,"net":296400,"cat_big":"베이커리","cat_mid":"브레드","cat_small":"일반빵"},{"store":"하남","item":"밤 식빵","qty":55,"net":385000,"cat_big":"베이커리","cat_mid":"브레드","cat_small":"일반빵"},{"store":"하남","item":"인크 로쉐","qty":28,"net":162400,"cat_big":"베이커리","cat_mid":"브레드","cat_small":"일반빵"},{"store":"하남","item":"커스타드 브레드","qty":80,"net":280000,"cat_big":"베이커리","cat_mid":"브레드","cat_small":"일반빵"},{"store":"하남","item":"딸기 초콜릿 롤 케이크(조각)","qty":25,"net":187500,"cat_big":"베이커리","cat_mid":"케이크","cat_small":"조각 케이크"},{"store":"하남","item":"두바이 퀸 아망","qty":50,"net":290000,"cat_big":"베이커리","cat_mid":"페이스트리","cat_small":"퀸 아망"},{"store":"하남","item":"스리라차 소시지 페이스트리","qty":45,"net":279000,"cat_big":"베이커리","cat_mid":"페이스트리","cat_small":"크루아상 계열"},{"store":"하남","item":"몽블랑 데니쉬","qty":60,"net":372000,"cat_big":"베이커리","cat_mid":"페이스트리","cat_small":"데니쉬"},{"store":"하남","item":"딸기 커스터드 턴오버","qty":40,"net":232000,"cat_big":"베이커리","cat_mid":"페이스트리","cat_small":"크루아상 계열"},{"store":"광주","item":"상하목장_딸기 아이스크림","qty":18,"net":86400,"cat_big":"RTD","cat_mid":"음료","cat_small":"RTD음료"},{"store":"광주","item":"락앤락475ml(이의리)","qty":10,"net":410000,"cat_big":"MD/기타","cat_mid":"MD","cat_small":"텀블러"},{"store":"광주","item":"락앤락475ml(최지민)","qty":5,"net":205000,"cat_big":"MD/기타","cat_mid":"MD","cat_small":"텀블러"},{"store":"광주","item":"다크 오리진블렌드 200g","qty":5,"net":80000,"cat_big":"MD/기타","cat_mid":"MD","cat_small":"커피류"},{"store":"광주","item":"SLV 말라카라C파카마라N 200g","qty":3,"net":54000,"cat_big":"MD/기타","cat_mid":"MD","cat_small":"커피류"},{"store":"광주","item":"리유저블백(M)","qty":28,"net":84000,"cat_big":"MD/기타","cat_mid":"MD","cat_small":"기타"},{"store":"광주","item":"쇼핑백(감광지화이트)","qty":160,"net":32000,"cat_big":"MD/기타","cat_mid":"MD","cat_small":"포장"},{"store":"광주","item":"야구공빵 박스","qty":21,"net":21000,"cat_big":"MD/기타","cat_mid":"MD","cat_small":"포장"},{"store":"광주","item":"타이거즈 로고볼(소형)","qty":320,"net":1920000,"cat_big":"MD/기타","cat_mid":"MD","cat_small":"KIA Tigers"},{"store":"광주","item":"T로고볼 키링","qty":44,"net":264000,"cat_big":"MD/기타","cat_mid":"MD","cat_small":"KIA Tigers"},{"store":"광주","item":"브레드이발소(오렌지망고)","qty":94,"net":159800,"cat_big":"RTD","cat_mid":"음료","cat_small":"RTD음료"},{"store":"광주","item":"브레드이발소(포도사과)","qty":97,"net":164900,"cat_big":"RTD","cat_mid":"음료","cat_small":"RTD음료"},{"store":"광주","item":"에비앙 500","qty":48,"net":120000,"cat_big":"RTD","cat_mid":"음료","cat_small":"RTD음료"},{"store":"광주","item":"유기농 우유 125ML","qty":46,"net":92000,"cat_big":"RTD","cat_mid":"음료","cat_small":"RTD음료"},{"store":"광주","item":"유기농 딸기우유 125ML","qty":56,"net":112000,"cat_big":"RTD","cat_mid":"음료","cat_small":"RTD음료"},{"store":"광주","item":"자카파_밀크","qty":159,"net":1272000,"cat_big":"음료","cat_mid":"공통","cat_small":"시그니처"},{"store":"광주","item":"I 아메리카노(R)","qty":95,"net":646000,"cat_big":"음료","cat_mid":"공통","cat_small":"시그니처"},{"store":"광주","item":"카페라떼(R)","qty":26,"net":176800,"cat_big":"음료","cat_mid":"공통","cat_small":"시그니처"},{"store":"광주","item":"I 카페라떼(R)","qty":26,"net":176800,"cat_big":"음료","cat_mid":"공통","cat_small":"시그니처"},{"store":"광주","item":"I 과테말라 럼배럴","qty":7,"net":56000,"cat_big":"음료","cat_mid":"공통","cat_small":"드립커피"},{"store":"광주","item":"I 엘살바도르 파카마라 내추럴","qty":5,"net":32500,"cat_big":"음료","cat_mid":"공통","cat_small":"드립커피"},{"store":"광주","item":"I 에티오피아 코케허니","qty":20,"net":130000,"cat_big":"음료","cat_mid":"공통","cat_small":"드립커피"},{"store":"광주","item":"아메리카노(D)","qty":152,"net":820800,"cat_big":"음료","cat_mid":"공통","cat_small":"커피"},{"store":"광주","item":"아메리카노(INC)","qty":467,"net":2521800,"cat_big":"음료","cat_mid":"공통","cat_small":"커피"},{"store":"광주","item":"아메리카노(DARK)","qty":292,"net":1576800,"cat_big":"음료","cat_mid":"공통","cat_small":"커피"},{"store":"광주","item":"I 아메리카노(D)","qty":482,"net":2602800,"cat_big":"음료","cat_mid":"공통","cat_small":"커피"},{"store":"광주","item":"I 아메리카노(INC)","qty":1853,"net":10006200,"cat_big":"음료","cat_mid":"공통","cat_small":"커피"},{"store":"광주","item":"I 아메리카노(DARK)","qty":1718,"net":9277200,"cat_big":"음료","cat_mid":"공통","cat_small":"커피"},{"store":"광주","item":"+샷 추가","qty":24,"net":12000,"cat_big":"음료","cat_mid":"공통","cat_small":"커피"},{"store":"광주","item":"카페 라떼","qty":324,"net":1879200,"cat_big":"음료","cat_mid":"공통","cat_small":"커피"},{"store":"광주","item":"I 카페 라떼","qty":455,"net":2639000,"cat_big":"음료","cat_mid":"공통","cat_small":"커피"},{"store":"광주","item":"I 연유 라떼","qty":174,"net":1131000,"cat_big":"음료","cat_mid":"공통","cat_small":"커피"},{"store":"광주","item":"바닐라빈 라떼","qty":105,"net":682500,"cat_big":"음료","cat_mid":"공통","cat_small":"커피"},{"store":"광주","item":"I 바닐라빈 라떼","qty":456,"net":2964000,"cat_big":"음료","cat_mid":"공통","cat_small":"커피"},{"store":"광주","item":"I 카페 모카","qty":53,"net":344500,"cat_big":"음료","cat_mid":"공통","cat_small":"커피"},{"store":"광주","item":"카라멜 마끼아또","qty":16,"net":104000,"cat_big":"음료","cat_mid":"공통","cat_small":"커피"},{"store":"광주","item":"I 카라멜 마끼아또","qty":107,"net":695500,"cat_big":"음료","cat_mid":"공통","cat_small":"커피"},{"store":"광주","item":"제주 한라봉 블랜디드","qty":566,"net":4245000,"cat_big":"음료","cat_mid":"공통","cat_small":"블랜디드"},{"store":"광주","item":"청포도 라임 에이드","qty":450,"net":3375000,"cat_big":"음료","cat_mid":"공통","cat_small":"에이드"},{"store":"광주","item":"시트러스 주스","qty":290,"net":2175000,"cat_big":"음료","cat_mid":"공통","cat_small":"주스"},{"store":"광주","item":"초코 라떼","qty":53,"net":360400,"cat_big":"음료","cat_mid":"공통","cat_small":"논커피"},{"store":"광주","item":"I 초코 라떼","qty":401,"net":2726800,"cat_big":"음료","cat_mid":"공통","cat_small":"논커피"},{"store":"광주","item":"제주 말차 라떼","qty":76,"net":516800,"cat_big":"음료","cat_mid":"공통","cat_small":"논커피"},{"store":"광주","item":"I 제주 말차 라떼","qty":283,"net":1924400,"cat_big":"음료","cat_mid":"공통","cat_small":"논커피"},{"store":"광주","item":"세러니티","qty":63,"net":365400,"cat_big":"음료","cat_mid":"공통","cat_small":"차"},{"store":"광주","item":"I 세러니티","qty":56,"net":324800,"cat_big":"음료","cat_mid":"공통","cat_small":"차"},{"store":"광주","item":"크림슨펀치","qty":31,"net":179800,"cat_big":"음료","cat_mid":"공통","cat_small":"차"},{"store":"광주","item":"I 크림슨펀치","qty":35,"net":203000,"cat_big":"음료","cat_mid":"공통","cat_small":"차"},{"store":"광주","item":"얼그레이","qty":20,"net":116000,"cat_big":"음료","cat_mid":"공통","cat_small":"차"},{"store":"광주","item":"I 얼그레이","qty":28,"net":162400,"cat_big":"음료","cat_mid":"공통","cat_small":"차"},{"store":"광주","item":"I 피치우롱","qty":105,"net":609000,"cat_big":"음료","cat_mid":"공통","cat_small":"차"},{"store":"광주","item":"인크 부스터","qty":90,"net":675000,"cat_big":"음료","cat_mid":"스페셜","cat_small":"광주"},{"store":"광주","item":"H 애플 시나몬 세러니티","qty":55,"net":357500,"cat_big":"음료","cat_mid":"스페셜","cat_small":"시즌음료"},{"store":"광주","item":"I 애플 시나몬 세러니티","qty":83,"net":539500,"cat_big":"음료","cat_mid":"스페셜","cat_small":"시즌음료"},{"store":"광주","item":"얼그레이 그린플럼티","qty":140,"net":910000,"cat_big":"음료","cat_mid":"스페셜","cat_small":"시즌음료"},{"store":"광주","item":"콘 크러쉬 블렌디드","qty":95,"net":551000,"cat_big":"음료","cat_mid":"공통","cat_small":"블랜디드"},{"store":"광주","item":"애플 시나몬 크럼블 아이스크림 추가","qty":60,"net":60000,"cat_big":"음료","cat_mid":"스페셜","cat_small":"시즌음료"},{"store":"광주","item":"레몬 마들렌","qty":142,"net":539600,"cat_big":"베이커리","cat_mid":"구움과자","cat_small":"마들렌"},{"store":"광주","item":"초콜릿 마들렌","qty":57,"net":216600,"cat_big":"베이커리","cat_mid":"구움과자","cat_small":"마들렌"},{"store":"광주","item":"커피 피칸 마들렌","qty":49,"net":171500,"cat_big":"베이커리","cat_mid":"구움과자","cat_small":"마들렌"},{"store":"광주","item":"크런치 땅콩 마들렌","qty":39,"net":136500,"cat_big":"베이커리","cat_mid":"구움과자","cat_small":"마들렌"},{"store":"광주","item":"레몬 버터 바","qty":47,"net":178600,"cat_big":"베이커리","cat_mid":"구움과자","cat_small":"버터바"},{"store":"광주","item":"민트 초콜릿 오레오 바","qty":26,"net":98800,"cat_big":"베이커리","cat_mid":"구움과자","cat_small":"버터바"},{"store":"광주","item":"피넛 버터 바","qty":54,"net":205200,"cat_big":"베이커리","cat_mid":"구움과자","cat_small":"버터바"},{"store":"광주","item":"버터 사블레","qty":31,"net":86800,"cat_big":"베이커리","cat_mid":"구움과자","cat_small":"사블레"},{"store":"광주","item":"바닐라 사블레","qty":12,"net":33600,"cat_big":"베이커리","cat_mid":"구움과자","cat_small":"사블레"},{"store":"광주","item":"솔티드 초콜릿 사블레","qty":27,"net":75600,"cat_big":"베이커리","cat_mid":"구움과자","cat_small":"사블레"},{"store":"광주","item":"바질 치즈 스콘","qty":26,"net":124800,"cat_big":"베이커리","cat_mid":"구움과자","cat_small":"스콘"},{"store":"광주","item":"플레인 버터 스콘","qty":39,"net":187200,"cat_big":"베이커리","cat_mid":"구움과자","cat_small":"스콘"},{"store":"광주","item":"크렌베리 화이트 초콜릿 스콘","qty":30,"net":156000,"cat_big":"베이커리","cat_mid":"구움과자","cat_small":"스콘"},{"store":"광주","item":"애플잼 스콘","qty":173,"net":865000,"cat_big":"베이커리","cat_mid":"구움과자","cat_small":"스콘"},{"store":"광주","item":"더블 초콜릿 쿠키","qty":57,"net":239400,"cat_big":"베이커리","cat_mid":"구움과자","cat_small":"쿠키"},{"store":"광주","item":"크랜베리 아몬드 쿠키N","qty":38,"net":144400,"cat_big":"베이커리","cat_mid":"구움과자","cat_small":"쿠키"},{"store":"광주","item":"레몬 파운드","qty":109,"net":490500,"cat_big":"베이커리","cat_mid":"구움과자","cat_small":"파운드"},{"store":"광주","item":"얼 그레이 파운드","qty":58,"net":261000,"cat_big":"베이커리","cat_mid":"구움과자","cat_small":"파운드"},{"store":"광주","item":"플레인 휘낭시에","qty":107,"net":406600,"cat_big":"베이커리","cat_mid":"구움과자","cat_small":"휘낭시에"},{"store":"광주","item":"소금 초콜릿 휘낭시에","qty":95,"net":380000,"cat_big":"베이커리","cat_mid":"구움과자","cat_small":"휘낭시에"},{"store":"광주","item":"헤이즐넛 오렌지 휘낭시에","qty":47,"net":164500,"cat_big":"베이커리","cat_mid":"구움과자","cat_small":"휘낭시에"},{"store":"광주","item":"인크 망디앙 휘낭시에","qty":43,"net":172000,"cat_big":"베이커리","cat_mid":"구움과자","cat_small":"휘낭시에"},{"store":"광주","item":"무화과 크림 치즈 휘낭시에","qty":102,"net":387600,"cat_big":"베이커리","cat_mid":"구움과자","cat_small":"휘낭시에"},{"store":"광주","item":"애플 시나몬 크럼블","qty":216,"net":1188000,"cat_big":"베이커리","cat_mid":"구움과자","cat_small":"크럼블"},{"store":"광주","item":"무화과 샤워도우","qty":45,"net":360000,"cat_big":"베이커리","cat_mid":"브레드","cat_small":"건강빵"},{"store":"광주","item":"미니 무화과 샤워도우","qty":155,"net":589000,"cat_big":"베이커리","cat_mid":"브레드","cat_small":"건강빵"},{"store":"광주","item":"플레인 베이글","qty":102,"net":408000,"cat_big":"베이커리","cat_mid":"브레드","cat_small":"베이글"},{"store":"광주","item":"더블 베리 베이글","qty":113,"net":542400,"cat_big":"베이커리","cat_mid":"브레드","cat_small":"베이글"},{"store":"광주","item":"라우겐 베이글","qty":100,"net":450000,"cat_big":"베이커리","cat_mid":"브레드","cat_small":"베이글"},{"store":"광주","item":"어니언 베이글","qty":62,"net":279000,"cat_big":"베이커리","cat_mid":"브레드","cat_small":"베이글"},{"store":"광주","item":"페퍼로니 할라피뇨 베이글","qty":164,"net":852800,"cat_big":"베이커리","cat_mid":"브레드","cat_small":"베이글"},{"store":"광주","item":"치즈 포테이토 베이글","qty":103,"net":618000,"cat_big":"베이커리","cat_mid":"브레드","cat_small":"베이글"},{"store":"광주","item":"버터 라우겐 베이글","qty":80,"net":496000,"cat_big":"베이커리","cat_mid":"브레드","cat_small":"베이글"},{"store":"광주","item":"어니언 크림 치즈 베이글","qty":146,"net":1051200,"cat_big":"베이커리","cat_mid":"브레드","cat_small":"베이글"},{"store":"광주","item":"쪽파 크림 치즈 베이글","qty":185,"net":1387500,"cat_big":"베이커리","cat_mid":"브레드","cat_small":"베이글"},{"store":"광주","item":"바질 토마토 베이글","qty":88,"net":396000,"cat_big":"베이커리","cat_mid":"브레드","cat_small":"베이글"},{"store":"광주","item":"갈릭 베이글","qty":159,"net":763200,"cat_big":"베이커리","cat_mid":"브레드","cat_small":"베이글"},{"store":"광주","item":"얼 그레이 무화과 베이글","qty":112,"net":504000,"cat_big":"베이커리","cat_mid":"브레드","cat_small":"베이글"},{"store":"광주","item":"올리브 베이글","qty":136,"net":571200,"cat_big":"베이커리","cat_mid":"브레드","cat_small":"베이글"},{"store":"광주","item":"모카 베이글","qty":58,"net":301600,"cat_big":"베이커리","cat_mid":"브레드","cat_small":"베이글"},{"store":"광주","item":"불고기 브리 치즈 샌드위치","qty":46,"net":450800,"cat_big":"베이커리","cat_mid":"브레드","cat_small":"샌드위치"},{"store":"광주","item":"에그 베이컨 베이글 샌드위치","qty":68,"net":666400,"cat_big":"베이커리","cat_mid":"브레드","cat_small":"샌드위치"},{"store":"광주","item":"플레인 소금빵","qty":958,"net":4023600,"cat_big":"베이커리","cat_mid":"브레드","cat_small":"소금빵"},{"store":"광주","item":"갈릭 소금빵","qty":155,"net":744000,"cat_big":"베이커리","cat_mid":"브레드","cat_small":"소금빵"},{"store":"광주","item":"소시지 소금빵","qty":127,"net":609600,"cat_big":"베이커리","cat_mid":"브레드","cat_small":"소금빵"},{"store":"광주","item":"아몬드 소금빵","qty":114,"net":547200,"cat_big":"베이커리","cat_mid":"브레드","cat_small":"소금빵"},{"store":"광주","item":"우유 크림 소금빵","qty":287,"net":1435000,"cat_big":"베이커리","cat_mid":"브레드","cat_small":"소금빵"},{"store":"광주","item":"앙버터 소금빵","qty":207,"net":1076400,"cat_big":"베이커리","cat_mid":"브레드","cat_small":"소금빵"},{"store":"광주","item":"명란 소금빵","qty":486,"net":2332800,"cat_big":"베이커리","cat_mid":"브레드","cat_small":"소금빵"},{"store":"광주","item":"카스텔라 소금빵","qty":122,"net":634400,"cat_big":"베이커리","cat_mid":"브레드","cat_small":"소금빵"},{"store":"광주","item":"수제 단팥빵","qty":185,"net":703000,"cat_big":"베이커리","cat_mid":"브레드","cat_small":"일반빵"},{"store":"광주","item":"야구공빵","qty":1106,"net":5530000,"cat_big":"베이커리","cat_mid":"브레드","cat_small":"일반빵"},{"store":"광주","item":"초콜릿 야구공빵","qty":864,"net":4320000,"cat_big":"베이커리","cat_mid":"브레드","cat_small":"일반빵"},{"store":"광주","item":"버터 크림 브레드","qty":97,"net":339500,"cat_big":"베이커리","cat_mid":"브레드","cat_small":"일반빵"},{"store":"광주","item":"야구공빵 세트_4입(5%)","qty":421,"net":7999000,"cat_big":"베이커리","cat_mid":"브레드","cat_small":"일반빵"},{"store":"광주","item":"복숭아 요거트 야구공빵","qty":472,"net":2360000,"cat_big":"베이커리","cat_mid":"브레드","cat_small":"일반빵"},{"store":"광주","item":"블루베리 크림 치즈","qty":17,"net":51000,"cat_big":"베이커리","cat_mid":"스프레드/잼/오일","cat_small":"크림 치즈"},{"store":"광주","item":"연유 크림 치즈","qty":2,"net":6000,"cat_big":"베이커리","cat_mid":"스프레드/잼/오일","cat_small":"크림 치즈"},{"store":"광주","item":"썸머 시트러스(샌드)","qty":91,"net":637000,"cat_big":"베이커리","cat_mid":"케이크","cat_small":"그 외 케이크"},{"store":"광주","item":"무화과 생크림 케이크 (조각)","qty":116,"net":1102000,"cat_big":"베이커리","cat_mid":"케이크","cat_small":"조각 케이크"},{"store":"광주","item":"몽블랑 (조각)","qty":63,"net":598500,"cat_big":"베이커리","cat_mid":"케이크","cat_small":"조각 케이크"},{"store":"광주","item":"블루베리 데니쉬","qty":69,"net":496800,"cat_big":"베이커리","cat_mid":"페이스트리","cat_small":"데니쉬"},{"store":"광주","item":"츄러스 데니쉬","qty":42,"net":285600,"cat_big":"베이커리","cat_mid":"페이스트리","cat_small":"데니쉬"},{"store":"광주","item":"얼 그레이 무화과 데니쉬","qty":85,"net":637500,"cat_big":"베이커리","cat_mid":"페이스트리","cat_small":"데니쉬"},{"store":"광주","item":"썸머 후르츠 데니쉬","qty":61,"net":457500,"cat_big":"베이커리","cat_mid":"페이스트리","cat_small":"데니쉬"},{"store":"광주","item":"플레인 퀸 아망","qty":238,"net":1142400,"cat_big":"베이커리","cat_mid":"페이스트리","cat_small":"퀸 아망"},{"store":"광주","item":"초콜릿 퀸 아망","qty":93,"net":483600,"cat_big":"베이커리","cat_mid":"페이스트리","cat_small":"퀸 아망"},{"store":"광주","item":"해피 벌스데이 퀸 아망","qty":34,"net":176800,"cat_big":"베이커리","cat_mid":"페이스트리","cat_small":"퀸 아망"},{"store":"광주","item":"두바이 퀸 아망","qty":99,"net":574200,"cat_big":"베이커리","cat_mid":"페이스트리","cat_small":"퀸 아망"},{"store":"광주","item":"플레인 크루아상","qty":108,"net":486000,"cat_big":"베이커리","cat_mid":"페이스트리","cat_small":"크루아상 계열"},{"store":"광주","item":"뺑 오 쇼콜라","qty":164,"net":852800,"cat_big":"베이커리","cat_mid":"페이스트리","cat_small":"크루아상 계열"},{"store":"광주","item":"뉴욕 페이스트리","qty":169,"net":929500,"cat_big":"베이커리","cat_mid":"페이스트리","cat_small":"크루아상 계열"},{"store":"광주","item":"스리라차 소시지 페이스트리","qty":295,"net":1829000,"cat_big":"베이커리","cat_mid":"페이스트리","cat_small":"크루아상 계열"},{"store":"광주","item":"맘모스 페이스트리","qty":73,"net":379600,"cat_big":"베이커리","cat_mid":"페이스트리","cat_small":"크루아상 계열"},{"store":"광주","item":"애플 턴오버","qty":112,"net":728000,"cat_big":"베이커리","cat_mid":"페이스트리","cat_small":"크루아상 계열"},{"store":"광주","item":"초콜릿 크룽지","qty":99,"net":475200,"cat_big":"베이커리","cat_mid":"페이스트리","cat_small":"크루아상 계열"},{"store":"광주","item":"시나몬 크룽지","qty":111,"net":499500,"cat_big":"베이커리","cat_mid":"페이스트리","cat_small":"크루아상 계열"},{"store":"광주","item":"캔맥주(테라 500)","qty":25,"net":75000,"cat_big":"RTD","cat_mid":"주류","cat_small":"주류"},{"store":"광주","item":"딸기 슬러쉬","qty":50,"net":275000,"cat_big":"MD/기타","cat_mid":"투고존","cat_small":"슬러시"},{"store":"광주","item":"무알콜 하이트","qty":41,"net":102500,"cat_big":"음료","cat_mid":"스페셜","cat_small":"맥주"},{"store":"광주","item":"애플 망고 슬러쉬","qty":87,"net":478500,"cat_big":"음료","cat_mid":"스페셜","cat_small":"투고"},{"store":"광주","item":"(칵)애플 망고 슬러쉬","qty":22,"net":121000,"cat_big":"음료","cat_mid":"스페셜","cat_small":"투고"},{"store":"가산","item":"에티오피아 커피백(페도라형)","qty":31,"net":62000,"cat_big":"MD/기타","cat_mid":"MD","cat_small":"커피류"},{"store":"가산","item":"인크 프렌치바닐라라떼(10입)","qty":12,"net":108000,"cat_big":"MD/기타","cat_mid":"MD","cat_small":"커피류"},{"store":"가산","item":"인크 클래식핫초코(10입)","qty":3,"net":27000,"cat_big":"MD/기타","cat_mid":"MD","cat_small":"커피류"},{"store":"가산","item":"인크 오리진블렌드 200g","qty":46,"net":736000,"cat_big":"MD/기타","cat_mid":"MD","cat_small":"커피류"},{"store":"가산","item":"리유저블백(L)","qty":4,"net":8000,"cat_big":"MD/기타","cat_mid":"MD","cat_small":"기타"},{"store":"가산","item":"I 콤롬비아 에르모소","qty":28,"net":196000,"cat_big":"음료","cat_mid":"공통","cat_small":"드립커피"},{"store":"가산","item":"I 에티오피아 코케허니(SP)","qty":2,"net":16000,"cat_big":"음료","cat_mid":"공통","cat_small":"싸이폰"},{"store":"가산","item":"에스프레소(D)","qty":8,"net":43200,"cat_big":"음료","cat_mid":"공통","cat_small":"커피"},{"store":"가산","item":"에스프레소(INC)","qty":19,"net":102600,"cat_big":"음료","cat_mid":"공통","cat_small":"커피"},{"store":"가산","item":"+샷 추가","qty":25,"net":12500,"cat_big":"음료","cat_mid":"공통","cat_small":"커피"},{"store":"가산","item":"카라멜 마끼아또","qty":27,"net":175500,"cat_big":"음료","cat_mid":"공통","cat_small":"커피"},{"store":"가산","item":"I 카라멜 마끼아또","qty":33,"net":214500,"cat_big":"음료","cat_mid":"공통","cat_small":"커피"},{"store":"가산","item":"에스프레소(R)","qty":28,"net":190400,"cat_big":"음료","cat_mid":"공통","cat_small":"커피"},{"store":"가산","item":"초코 라떼","qty":34,"net":231200,"cat_big":"음료","cat_mid":"공통","cat_small":"논커피"},{"store":"가산","item":"헤이즐넛 오렌지 휘낭시에","qty":40,"net":140000,"cat_big":"베이커리","cat_mid":"구움과자","cat_small":"휘낭시에"},{"store":"가산","item":"크랜베리 사워도우","qty":64,"net":332800,"cat_big":"베이커리","cat_mid":"브레드","cat_small":"건강빵"},{"store":"가산","item":"먹물 롤 치즈 치아바타","qty":166,"net":697200,"cat_big":"베이커리","cat_mid":"브레드","cat_small":"건강빵"},{"store":"가산","item":"올리브 치즈 치아바타","qty":202,"net":909000,"cat_big":"베이커리","cat_mid":"브레드","cat_small":"건강빵"},{"store":"가산","item":"사워도우 스프레드 세트","qty":9,"net":67500,"cat_big":"베이커리","cat_mid":"브레드","cat_small":"건강빵"},{"store":"가산","item":"무화과 샤워도우","qty":78,"net":624000,"cat_big":"베이커리","cat_mid":"브레드","cat_small":"건강빵"},{"store":"가산","item":"플레인 크림 치즈","qty":12,"net":36000,"cat_big":"베이커리","cat_mid":"스프레드/잼/오일","cat_small":"크림 치즈"},{"store":"가산","item":"애플 시나몬 크림 치즈","qty":19,"net":57000,"cat_big":"베이커리","cat_mid":"스프레드/잼/오일","cat_small":"크림 치즈"},{"store":"가산","item":"발사믹 오일","qty":11,"net":18000,"cat_big":"베이커리","cat_mid":"스프레드/잼/오일","cat_small":"오일"},{"store":"가산","item":"몽블랑 (1호)","qty":14,"net":630000,"cat_big":"베이커리","cat_mid":"케이크","cat_small":"홀 케이크"},{"store":"가산","item":"블루베리 데니쉬","qty":89,"net":640800,"cat_big":"베이커리","cat_mid":"페이스트리","cat_small":"데니쉬"},{"store":"다산","item":"인크커피믹스(50입)","qty":4,"net":72000,"cat_big":"MD/기타","cat_mid":"MD","cat_small":"커피류"},{"store":"다산","item":"리유저블마켓백","qty":2,"net":24000,"cat_big":"MD/기타","cat_mid":"MD","cat_small":"기타"},{"store":"다산","item":"DRIP BAG VARIETY BOX","qty":6,"net":150000,"cat_big":"MD/기타","cat_mid":"MD","cat_small":"선물세트"},{"store":"다산","item":"200,000원","qty":2,"net":400000,"cat_big":"MD/기타","cat_mid":"기타","cat_small":"특판"},{"store":"다산","item":"아메리카노(R)","qty":74,"net":503200,"cat_big":"음료","cat_mid":"공통","cat_small":"시그니처"},{"store":"다산","item":"+샷 추가","qty":62,"net":31000,"cat_big":"음료","cat_mid":"공통","cat_small":"커피"},{"store":"다산","item":"I 연유 라떼","qty":172,"net":1118000,"cat_big":"음료","cat_mid":"공통","cat_small":"커피"},{"store":"다산","item":"I 카페 모카","qty":71,"net":461500,"cat_big":"음료","cat_mid":"공통","cat_small":"커피"},{"store":"다산","item":"카라멜 마끼아또","qty":40,"net":260000,"cat_big":"음료","cat_mid":"공통","cat_small":"커피"},{"store":"다산","item":"겐마이차","qty":71,"net":411800,"cat_big":"음료","cat_mid":"공통","cat_small":"차"},{"store":"다산","item":"피치우롱","qty":121,"net":701800,"cat_big":"음료","cat_mid":"공통","cat_small":"차"},{"store":"다산","item":"레몬 버터 바","qty":46,"net":174800,"cat_big":"베이커리","cat_mid":"구움과자","cat_small":"버터바"},{"store":"다산","item":"피넛 버터 바","qty":45,"net":171000,"cat_big":"베이커리","cat_mid":"구움과자","cat_small":"버터바"},{"store":"다산","item":"얼 그레이 파운드","qty":167,"net":751500,"cat_big":"베이커리","cat_mid":"구움과자","cat_small":"파운드"},{"store":"다산","item":"플레인 휘낭시에","qty":92,"net":349600,"cat_big":"베이커리","cat_mid":"구움과자","cat_small":"휘낭시에"},{"store":"다산","item":"얼 그레이 휘낭시에","qty":59,"net":236000,"cat_big":"베이커리","cat_mid":"구움과자","cat_small":"휘낭시에"},{"store":"다산","item":"크랜베리 호두 깜파뉴","qty":113,"net":655400,"cat_big":"베이커리","cat_mid":"브레드","cat_small":"건강빵"},{"store":"다산","item":"누텔라 소금빵","qty":92,"net":460000,"cat_big":"베이커리","cat_mid":"브레드","cat_small":"소금빵"},{"store":"다산","item":"플레인 크림 치즈","qty":67,"net":201000,"cat_big":"베이커리","cat_mid":"스프레드/잼/오일","cat_small":"크림 치즈"},{"store":"다산","item":"블루베리 크림 치즈","qty":59,"net":177000,"cat_big":"베이커리","cat_mid":"스프레드/잼/오일","cat_small":"크림 치즈"},{"store":"다산","item":"아보카도 에그 오픈 토스트","qty":127,"net":2032000,"cat_big":"푸드","cat_mid":"다산 푸드","cat_small":"브런치"},{"store":"다산","item":"훈제 연어 크로와상 샌드위치","qty":46,"net":782000,"cat_big":"푸드","cat_mid":"다산 푸드","cat_small":"브런치"},{"store":"다산","item":"뽀로로음료(밀크)","qty":67,"net":167500,"cat_big":"RTD","cat_mid":"음료","cat_small":"RTD음료"},{"store":"다산","item":"SLV 말라카라C파카마라N 200g","qty":4,"net":72000,"cat_big":"MD/기타","cat_mid":"MD","cat_small":"커피류"},{"store":"다산","item":"라임 로마노","qty":14,"net":86800,"cat_big":"음료","cat_mid":"스페셜","cat_small":"에쏘바"},{"store":"다산","item":"인크 콘파냐","qty":32,"net":198400,"cat_big":"음료","cat_mid":"스페셜","cat_small":"에쏘바"},{"store":"다산","item":"싱글 카푸치노","qty":46,"net":285200,"cat_big":"음료","cat_mid":"스페셜","cat_small":"에쏘바"},{"store":"수원","item":"ETH 예가체프 코케허니G1(N)200g","qty":14,"net":259000,"cat_big":"MD/기타","cat_mid":"MD","cat_small":"커피류"},{"store":"수원","item":"유기농 딸기우유 125ML","qty":97,"net":194000,"cat_big":"RTD","cat_mid":"음료","cat_small":"RTD음료"},{"store":"수원","item":"유기농 바나나우유 125ML","qty":50,"net":100000,"cat_big":"RTD","cat_mid":"음료","cat_small":"RTD음료"},{"store":"수원","item":"I 과테말라 럼배럴","qty":52,"net":416000,"cat_big":"음료","cat_mid":"공통","cat_small":"드립커피"},{"store":"수원","item":"I 콤롬비아 에르모소","qty":26,"net":182000,"cat_big":"음료","cat_mid":"공통","cat_small":"드립커피"},{"store":"수원","item":"아메리카노_UP(D)","qty":38,"net":224200,"cat_big":"음료","cat_mid":"공통","cat_small":"커피"},{"store":"수원","item":"+샷 추가","qty":40,"net":20000,"cat_big":"음료","cat_mid":"공통","cat_small":"커피"},{"store":"수원","item":"연유 라떼","qty":40,"net":260000,"cat_big":"음료","cat_mid":"공통","cat_small":"커피"},{"store":"수원","item":"카페 모카","qty":43,"net":279500,"cat_big":"음료","cat_mid":"공통","cat_small":"커피"},{"store":"수원","item":"I 카페 모카","qty":78,"net":507000,"cat_big":"음료","cat_mid":"공통","cat_small":"커피"},{"store":"수원","item":"카라멜 마끼아또","qty":37,"net":240500,"cat_big":"음료","cat_mid":"공통","cat_small":"커피"},{"store":"수원","item":"I 카라멜 마끼아또","qty":114,"net":741000,"cat_big":"음료","cat_mid":"공통","cat_small":"커피"},{"store":"수원","item":"밀크티","qty":31,"net":210800,"cat_big":"음료","cat_mid":"공통","cat_small":"논커피"},{"store":"수원","item":"I 겐마이차","qty":31,"net":179800,"cat_big":"음료","cat_mid":"공통","cat_small":"차"},{"store":"수원","item":"펫푸치노","qty":5,"net":26500,"cat_big":"음료","cat_mid":"스페셜","cat_small":"펫음료"},{"store":"수원","item":"H 애플 시나몬 세러니티","qty":48,"net":312000,"cat_big":"음료","cat_mid":"스페셜","cat_small":"시즌음료"},{"store":"수원","item":"콘 크러쉬 블렌디드","qty":125,"net":725000,"cat_big":"음료","cat_mid":"공통","cat_small":"블랜디드"},{"store":"하남","item":"인크 프렌치바닐라라떼(10입)","qty":3,"net":27000,"cat_big":"MD/기타","cat_mid":"MD","cat_small":"커피류"},{"store":"하남","item":"인크 오리진블렌드 200g","qty":11,"net":176000,"cat_big":"MD/기타","cat_mid":"MD","cat_small":"커피류"},{"store":"하남","item":"I 과테말라 럼배럴","qty":10,"net":80000,"cat_big":"음료","cat_mid":"공통","cat_small":"드립커피"},{"store":"하남","item":"I 플랫 화이트","qty":27,"net":156600,"cat_big":"음료","cat_mid":"공통","cat_small":"커피"},{"store":"하남","item":"연유 라떼","qty":13,"net":84500,"cat_big":"음료","cat_mid":"공통","cat_small":"커피"},{"store":"하남","item":"청포도 라임 에이드","qty":24,"net":180000,"cat_big":"음료","cat_mid":"공통","cat_small":"에이드"},{"store":"하남","item":"I 제주 말차 라떼","qty":25,"net":170000,"cat_big":"음료","cat_mid":"공통","cat_small":"논커피"},{"store":"하남","item":"피치우롱","qty":26,"net":150800,"cat_big":"음료","cat_mid":"공통","cat_small":"차"},{"store":"하남","item":"얼그레이 그린플럼티","qty":26,"net":169000,"cat_big":"음료","cat_mid":"스페셜","cat_small":"시즌음료"},{"store":"하남","item":"소보로빵","qty":41,"net":155800,"cat_big":"베이커리","cat_mid":"브레드","cat_small":"일반빵"},{"store":"하남","item":"뉴욕 치즈 케이크(조각)","qty":19,"net":161500,"cat_big":"베이커리","cat_mid":"케이크","cat_small":"조각 케이크"},{"store":"광주","item":"인크커피믹스(30입)","qty":3,"net":36000,"cat_big":"MD/기타","cat_mid":"MD","cat_small":"커피류"},{"store":"광주","item":"콜롬비아 커피백(페도라형)","qty":29,"net":58000,"cat_big":"MD/기타","cat_mid":"MD","cat_small":"커피류"},{"store":"광주","item":"에티오피아 커피백(페도라형)","qty":37,"net":74000,"cat_big":"MD/기타","cat_mid":"MD","cat_small":"커피류"},{"store":"광주","item":"인크 프렌치바닐라라떼(10입)","qty":3,"net":27000,"cat_big":"MD/기타","cat_mid":"MD","cat_small":"커피류"},{"store":"광주","item":"인크 클래식핫초코(10입)","qty":6,"net":54000,"cat_big":"MD/기타","cat_mid":"MD","cat_small":"커피류"},{"store":"광주","item":"인크 리유저블텀블러","qty":19,"net":133000,"cat_big":"MD/기타","cat_mid":"MD","cat_small":"기타"},{"store":"광주","item":"아메리카노(R)","qty":32,"net":217600,"cat_big":"음료","cat_mid":"공통","cat_small":"시그니처"},{"store":"광주","item":"카페 모카","qty":24,"net":156000,"cat_big":"음료","cat_mid":"공통","cat_small":"커피"},{"store":"광주","item":"겐마이차","qty":7,"net":40600,"cat_big":"음료","cat_mid":"공통","cat_small":"차"},{"store":"광주","item":"피치우롱","qty":45,"net":261000,"cat_big":"음료","cat_mid":"공통","cat_small":"차"},{"store":"광주","item":"럼 마론 크림 라떼","qty":119,"net":952000,"cat_big":"음료","cat_mid":"스페셜","cat_small":"시즌음료"},{"store":"광주","item":"라임 바질 마들렌","qty":32,"net":121600,"cat_big":"베이커리","cat_mid":"구움과자","cat_small":"마들렌"},{"store":"광주","item":"레몬 블루베리 스콘","qty":27,"net":135000,"cat_big":"베이커리","cat_mid":"구움과자","cat_small":"스콘"},{"store":"광주","item":"하몽 무화과 샌드위치","qty":37,"net":362600,"cat_big":"베이커리","cat_mid":"브레드","cat_small":"샌드위치"},{"store":"광주","item":"플레인 크림 치즈","qty":8,"net":24000,"cat_big":"베이커리","cat_mid":"스프레드/잼/오일","cat_small":"크림 치즈"},{"store":"광주","item":"애플 시나몬 크림 치즈","qty":3,"net":9000,"cat_big":"베이커리","cat_mid":"스프레드/잼/오일","cat_small":"크림 치즈"},{"store":"광주","item":"캐러멜 넛츠 크림 페이스트리","qty":31,"net":186000,"cat_big":"베이커리","cat_mid":"페이스트리","cat_small":"크루아상 계열"},{"store":"광주","item":"호걸이 글라스","qty":13,"net":156000,"cat_big":"MD/기타","cat_mid":"MD","cat_small":"기타"},{"store":"광주","item":"(칵)딸기 슬러쉬","qty":18,"net":99000,"cat_big":"MD/기타","cat_mid":"기타","cat_small":"슬러시"},{"store":"가산","item":"과테말라 럼배럴 커피파우더","qty":14,"net":196000,"cat_big":"MD/기타","cat_mid":"MD","cat_small":"커피류"},{"store":"가산","item":"아메리카노_UP(D)","qty":2,"net":11800,"cat_big":"음료","cat_mid":"공통","cat_small":"커피"},{"store":"가산","item":"카페 모카","qty":34,"net":221000,"cat_big":"음료","cat_mid":"공통","cat_small":"커피"},{"store":"가산","item":"민트 초콜릿 오레오 바","qty":39,"net":148200,"cat_big":"베이커리","cat_mid":"구움과자","cat_small":"버터바"},{"store":"가산","item":"연유 크림 치즈","qty":7,"net":21000,"cat_big":"베이커리","cat_mid":"스프레드/잼/오일","cat_small":"크림 치즈"},{"store":"다산","item":"뽀로로음료(보리차)","qty":60,"net":150000,"cat_big":"RTD","cat_mid":"음료","cat_small":"RTD음료"},{"store":"다산","item":"인크커피믹스(30입)","qty":6,"net":72000,"cat_big":"MD/기타","cat_mid":"MD","cat_small":"커피류"},{"store":"다산","item":"인크 리유저블텀블러","qty":2,"net":14000,"cat_big":"MD/기타","cat_mid":"MD","cat_small":"기타"},{"store":"다산","item":"I 카페라떼(R)","qty":99,"net":673200,"cat_big":"음료","cat_mid":"공통","cat_small":"시그니처"},{"store":"다산","item":"H 엘살바도르 파카마라 내추럴","qty":27,"net":175500,"cat_big":"음료","cat_mid":"공통","cat_small":"드립커피"},{"store":"다산","item":"에스프레소(D)","qty":3,"net":16200,"cat_big":"음료","cat_mid":"공통","cat_small":"커피"},{"store":"다산","item":"베이비치노(밀크)","qty":42,"net":201600,"cat_big":"음료","cat_mid":"스페셜","cat_small":"키즈"},{"store":"다산","item":"I 베이비치노(밀크)","qty":28,"net":134400,"cat_big":"음료","cat_mid":"스페셜","cat_small":"키즈"},{"store":"다산","item":"커피 피칸 마들렌","qty":30,"net":105000,"cat_big":"베이커리","cat_mid":"구움과자","cat_small":"마들렌"},{"store":"다산","item":"라임 바질 마들렌","qty":38,"net":144400,"cat_big":"베이커리","cat_mid":"구움과자","cat_small":"마들렌"},{"store":"다산","item":"초콜릿 커스타드 브레드","qty":50,"net":175000,"cat_big":"베이커리","cat_mid":"브레드","cat_small":"일반빵"},{"store":"다산","item":"연유 크림 치즈","qty":20,"net":60000,"cat_big":"베이커리","cat_mid":"스프레드/잼/오일","cat_small":"크림 치즈"},{"store":"다산","item":"이즈니 포션버터10g","qty":14,"net":21000,"cat_big":"베이커리","cat_mid":"스프레드/잼/오일","cat_small":"버터"},{"store":"다산","item":"에스프레소(DARK)","qty":46,"net":248400,"cat_big":"음료","cat_mid":"공통","cat_small":"커피"},{"store":"다산","item":"코르타도","qty":28,"net":173600,"cat_big":"음료","cat_mid":"스페셜","cat_small":"에쏘바"},{"store":"수원","item":"크라프트 쇼핑백","qty":5,"net":1000,"cat_big":"MD/기타","cat_mid":"MD","cat_small":"포장"},{"store":"수원","item":"커피백 머그세트","qty":1,"net":32000,"cat_big":"MD/기타","cat_mid":"MD","cat_small":"선물세트"},{"store":"수원","item":"과테말라 럼배럴","qty":35,"net":280000,"cat_big":"음료","cat_mid":"공통","cat_small":"드립커피"},{"store":"수원","item":"H 콜롬비아 에르모소","qty":15,"net":105000,"cat_big":"음료","cat_mid":"공통","cat_small":"드립커피"},{"store":"수원","item":"I 엘살바도르 파카마라 내추럴","qty":33,"net":214500,"cat_big":"음료","cat_mid":"공통","cat_small":"드립커피"},{"store":"수원","item":"에스프레소(R)","qty":23,"net":156400,"cat_big":"음료","cat_mid":"공통","cat_small":"커피"},{"store":"수원","item":"I 크림슨펀치","qty":38,"net":220400,"cat_big":"음료","cat_mid":"공통","cat_small":"차"},{"store":"하남","item":"유기농 주스(애플디노)","qty":17,"net":42500,"cat_big":"RTD","cat_mid":"음료","cat_small":"RTD음료"},{"store":"하남","item":"I 에티오피아 코케허니","qty":40,"net":260000,"cat_big":"음료","cat_mid":"공통","cat_small":"드립커피"},{"store":"하남","item":"I 아메리카노_UP(D)","qty":2,"net":11800,"cat_big":"음료","cat_mid":"공통","cat_small":"커피"},{"store":"하남","item":"플랫 화이트","qty":59,"net":342200,"cat_big":"음료","cat_mid":"공통","cat_small":"커피"},{"store":"하남","item":"I 세러니티","qty":12,"net":69600,"cat_big":"음료","cat_mid":"공통","cat_small":"차"},{"store":"하남","item":"크림슨펀치","qty":14,"net":81200,"cat_big":"음료","cat_mid":"공통","cat_small":"차"},{"store":"하남","item":"I 피치우롱","qty":10,"net":58000,"cat_big":"음료","cat_mid":"공통","cat_small":"차"},{"store":"하남","item":"애플 시나몬 크럼블 아이스크림 추가","qty":14,"net":14000,"cat_big":"음료","cat_mid":"스페셜","cat_small":"시즌음료"},{"store":"하남","item":"소금빵 러스크","qty":19,"net":98800,"cat_big":"베이커리","cat_mid":"브레드","cat_small":"일반빵"},{"store":"하남","item":"뺑 오 쇼콜라","qty":19,"net":98800,"cat_big":"베이커리","cat_mid":"페이스트리","cat_small":"크루아상 계열"},{"store":"하남","item":"아몬드 크루아상","qty":47,"net":225600,"cat_big":"베이커리","cat_mid":"페이스트리","cat_small":"크루아상 계열"},{"store":"하남","item":"초콜릿 크룽지","qty":20,"net":96000,"cat_big":"베이커리","cat_mid":"페이스트리","cat_small":"크루아상 계열"},{"store":"광주","item":"바닐라시럽","qty":10,"net":10000,"cat_big":"음료","cat_mid":"공통","cat_small":"커피"},{"store":"광주","item":"상하목장_밀크 아이스크림","qty":22,"net":105600,"cat_big":"RTD","cat_mid":"음료","cat_small":"RTD음료"},{"store":"광주","item":"스탠리709ml(이의리)","qty":1,"net":58000,"cat_big":"MD/기타","cat_mid":"MD","cat_small":"텀블러"},{"store":"광주","item":"미르16oz(양현종)","qty":12,"net":576000,"cat_big":"MD/기타","cat_mid":"MD","cat_small":"텀블러"},{"store":"광주","item":"과테말라 럼배럴 커피파우더","qty":1,"net":14000,"cat_big":"MD/기타","cat_mid":"MD","cat_small":"커피류"},{"store":"광주","item":"인크커피믹스(50입)","qty":3,"net":54000,"cat_big":"MD/기타","cat_mid":"MD","cat_small":"커피류"},{"store":"광주","item":"그라운드 타이거즈(15T)","qty":1,"net":25000,"cat_big":"MD/기타","cat_mid":"MD","cat_small":"커피류"},{"store":"광주","item":"인크 오리진블렌드 200g","qty":4,"net":64000,"cat_big":"MD/기타","cat_mid":"MD","cat_small":"커피류"},{"store":"광주","item":"ETH 예가체프 코케허니G1(N)200g","qty":7,"net":129500,"cat_big":"MD/기타","cat_mid":"MD","cat_small":"커피류"},{"store":"광주","item":"에스프레소샷잔","qty":2,"net":12000,"cat_big":"MD/기타","cat_mid":"MD","cat_small":"기타"},{"store":"광주","item":"리유저블마켓백","qty":1,"net":12000,"cat_big":"MD/기타","cat_mid":"MD","cat_small":"기타"},{"store":"광주","item":"티켓파우치(W)","qty":7,"net":196000,"cat_big":"MD/기타","cat_mid":"MD","cat_small":"기타"},{"store":"광주","item":"보냉백1호(+아이스팩)","qty":4,"net":6000,"cat_big":"MD/기타","cat_mid":"MD","cat_small":"포장"},{"store":"광주","item":"호걸이 인형머리띠","qty":17,"net":238000,"cat_big":"MD/기타","cat_mid":"MD","cat_small":"KIA Tigers"},{"store":"광주","item":"폼배트(24인치)","qty":5,"net":100000,"cat_big":"MD/기타","cat_mid":"MD","cat_small":"KIA Tigers"},{"store":"광주","item":"과테말라 럼배럴","qty":7,"net":56000,"cat_big":"음료","cat_mid":"공통","cat_small":"드립커피"},{"store":"광주","item":"H 에티오피아 코케허니","qty":19,"net":123500,"cat_big":"음료","cat_mid":"공통","cat_small":"드립커피"},{"store":"광주","item":"연유 라떼","qty":21,"net":136500,"cat_big":"음료","cat_mid":"공통","cat_small":"커피"},{"store":"광주","item":"베리 퀸 아망","qty":21,"net":109200,"cat_big":"베이커리","cat_mid":"페이스트리","cat_small":"퀸 아망"},{"store":"가산","item":"콜롬비아 디카페인(200g)","qty":14,"net":252000,"cat_big":"MD/기타","cat_mid":"MD","cat_small":"커피류"},{"store":"가산","item":"SLV 말라카라C파카마라N 200g","qty":15,"net":270000,"cat_big":"MD/기타","cat_mid":"MD","cat_small":"커피류"},{"store":"가산","item":"I 과테말라 럼배럴(SP)","qty":6,"net":60000,"cat_big":"음료","cat_mid":"공통","cat_small":"싸이폰"},{"store":"가산","item":"아메리카노_UP(INC)","qty":16,"net":94400,"cat_big":"음료","cat_mid":"공통","cat_small":"커피"},{"store":"가산","item":"겐마이차","qty":32,"net":185600,"cat_big":"음료","cat_mid":"공통","cat_small":"차"},{"store":"가산","item":"H 애플 시나몬 세러니티","qty":48,"net":312000,"cat_big":"음료","cat_mid":"스페셜","cat_small":"시즌음료"},{"store":"다산","item":"드립백(타이거즈)","qty":1,"net":12000,"cat_big":"MD/기타","cat_mid":"MD","cat_small":"커피류"},{"store":"다산","item":"과테말라 럼배럴 커피파우더","qty":9,"net":126000,"cat_big":"MD/기타","cat_mid":"MD","cat_small":"커피류"},{"store":"다산","item":"론자카파 럼배럴 에이지드 200g","qty":6,"net":198000,"cat_big":"MD/기타","cat_mid":"MD","cat_small":"커피류"},{"store":"다산","item":"인크 클래식핫초코(10입)","qty":5,"net":45000,"cat_big":"MD/기타","cat_mid":"MD","cat_small":"커피류"},{"store":"다산","item":"카페 모카","qty":41,"net":266500,"cat_big":"음료","cat_mid":"공통","cat_small":"커피"},{"store":"다산","item":"크런치 땅콩 마들렌","qty":47,"net":164500,"cat_big":"베이커리","cat_mid":"구움과자","cat_small":"마들렌"},{"store":"다산","item":"소금빵 러스크","qty":37,"net":192400,"cat_big":"베이커리","cat_mid":"브레드","cat_small":"일반빵"},{"store":"다산","item":"애플 시나몬 크림 치즈","qty":26,"net":78000,"cat_big":"베이커리","cat_mid":"스프레드/잼/오일","cat_small":"크림 치즈"},{"store":"수원","item":"인크이지보틀","qty":2,"net":11000,"cat_big":"MD/기타","cat_mid":"MD","cat_small":"텀블러"},{"store":"수원","item":"다크 오리진블렌드 200g","qty":7,"net":112000,"cat_big":"MD/기타","cat_mid":"MD","cat_small":"커피류"},{"store":"수원","item":"I 콜롬비아 산추아리오 골드워시드","qty":27,"net":189000,"cat_big":"음료","cat_mid":"공통","cat_small":"드립커피"},{"store":"수원","item":"H 엘살바도르 파카마라 내추럴","qty":24,"net":156000,"cat_big":"음료","cat_mid":"공통","cat_small":"드립커피"},{"store":"수원","item":"에스프레소(INC)","qty":14,"net":75600,"cat_big":"음료","cat_mid":"공통","cat_small":"커피"},{"store":"수원","item":"겐마이차","qty":15,"net":87000,"cat_big":"음료","cat_mid":"공통","cat_small":"차"},{"store":"수원","item":"I 얼그레이","qty":48,"net":278400,"cat_big":"음료","cat_mid":"공통","cat_small":"차"},{"store":"하남","item":"인크 리유저블텀블러","qty":1,"net":7000,"cat_big":"MD/기타","cat_mid":"MD","cat_small":"기타"},{"store":"하남","item":"I 아메리카노_UP(INC)","qty":23,"net":135700,"cat_big":"음료","cat_mid":"공통","cat_small":"커피"},{"store":"하남","item":"제주 말차 라떼","qty":26,"net":176800,"cat_big":"음료","cat_mid":"공통","cat_small":"논커피"},{"store":"하남","item":"겐마이차","qty":13,"net":75400,"cat_big":"음료","cat_mid":"공통","cat_small":"차"},{"store":"하남","item":"H 애플 시나몬 세러니티","qty":21,"net":136500,"cat_big":"음료","cat_mid":"스페셜","cat_small":"시즌음료"},{"store":"하남","item":"커피 피칸 마들렌","qty":22,"net":77000,"cat_big":"베이커리","cat_mid":"구움과자","cat_small":"마들렌"},{"store":"하남","item":"솔티드 초콜릿 사블레","qty":16,"net":44800,"cat_big":"베이커리","cat_mid":"구움과자","cat_small":"사블레"},{"store":"하남","item":"크랜베리 아몬드 쿠키N","qty":26,"net":98800,"cat_big":"베이커리","cat_mid":"구움과자","cat_small":"쿠키"},{"store":"하남","item":"레몬 파운드","qty":42,"net":189000,"cat_big":"베이커리","cat_mid":"구움과자","cat_small":"파운드"},{"store":"광주","item":"와이드 마우스 블랙 16oz","qty":1,"net":36000,"cat_big":"MD/기타","cat_mid":"MD","cat_small":"텀블러"},{"store":"광주","item":"미르16oz(전상현)","qty":2,"net":96000,"cat_big":"MD/기타","cat_mid":"MD","cat_small":"텀블러"},{"store":"광주","item":"콜롬비아 디카페인(200g)","qty":1,"net":18000,"cat_big":"MD/기타","cat_mid":"MD","cat_small":"커피류"},{"store":"광주","item":"과테말라 럼배럴 에이지드 200g","qty":2,"net":66000,"cat_big":"MD/기타","cat_mid":"MD","cat_small":"커피류"},{"store":"광주","item":"호걸이 머그","qty":1,"net":13000,"cat_big":"MD/기타","cat_mid":"MD","cat_small":"기타"},{"store":"광주","item":"오렌지쇼핑백","qty":5,"net":2500,"cat_big":"MD/기타","cat_mid":"MD","cat_small":"포장"},{"store":"광주","item":"보냉백2호(+아이스팩)","qty":1,"net":1500,"cat_big":"MD/기타","cat_mid":"MD","cat_small":"포장"},{"store":"광주","item":"안전구(타이거즈 로고볼)","qty":1,"net":7000,"cat_big":"MD/기타","cat_mid":"MD","cat_small":"KIA Tigers"},{"store":"광주","item":"H 엘살바도르 파카마라 내추럴","qty":2,"net":13000,"cat_big":"음료","cat_mid":"공통","cat_small":"드립커피"},{"store":"광주","item":"I 겐마이차","qty":8,"net":46400,"cat_big":"음료","cat_mid":"공통","cat_small":"차"},{"store":"가산","item":"드립백(베이직)","qty":9,"net":99000,"cat_big":"MD/기타","cat_mid":"MD","cat_small":"커피류"},{"store":"가산","item":"I 콜롬비아 산추아리오 골드워시드","qty":14,"net":98000,"cat_big":"음료","cat_mid":"공통","cat_small":"드립커피"},{"store":"가산","item":"에스프레소(DARK)","qty":11,"net":59400,"cat_big":"음료","cat_mid":"공통","cat_small":"커피"},{"store":"가산","item":"허브 생크림","qty":1,"net":2000,"cat_big":"베이커리","cat_mid":"스프레드/잼/오일","cat_small":"크림 치즈"},{"store":"다산","item":"다크 오리진블렌드 200g","qty":8,"net":128000,"cat_big":"MD/기타","cat_mid":"MD","cat_small":"커피류"},{"store":"다산","item":"기프트카드3","qty":2,"net":100000,"cat_big":"MD/기타","cat_mid":"기타","cat_small":"기프트카드"},{"store":"다산","item":"민트 초콜릿 오레오 바","qty":19,"net":72200,"cat_big":"베이커리","cat_mid":"구움과자","cat_small":"버터바"},{"store":"수원","item":"얼그레이크림라떼","qty":33,"net":214500,"cat_big":"음료","cat_mid":"음료","cat_small":"시즌음료"},{"store":"수원","item":"COL 산추아리오 골드워시드 20g","qty":1,"net":3000,"cat_big":"MD/기타","cat_mid":"MD","cat_small":"커피류"},{"store":"수원","item":"콜롬비아 산추아리오 골드워시드","qty":13,"net":91000,"cat_big":"음료","cat_mid":"공통","cat_small":"드립커피"},{"store":"수원","item":"펫랫화이트","qty":14,"net":67200,"cat_big":"음료","cat_mid":"스페셜","cat_small":"펫음료"},{"store":"하남","item":"와이드 마우스 화이트 16oz","qty":2,"net":76000,"cat_big":"MD/기타","cat_mid":"MD","cat_small":"텀블러"},{"store":"하남","item":"SLV 말라카라C파카마라N 200g","qty":6,"net":108000,"cat_big":"MD/기타","cat_mid":"MD","cat_small":"커피류"},{"store":"하남","item":"바이트 박스","qty":5,"net":5000,"cat_big":"MD/기타","cat_mid":"MD","cat_small":"포장"},{"store":"하남","item":"쇼핑백(흰) 중","qty":1,"net":1000,"cat_big":"MD/기타","cat_mid":"MD","cat_small":"포장"},{"store":"하남","item":"카라멜 마끼아또","qty":12,"net":78000,"cat_big":"음료","cat_mid":"공통","cat_small":"커피"},{"store":"하남","item":"자몽 에이드","qty":14,"net":105000,"cat_big":"음료","cat_mid":"공통","cat_small":"에이드"},{"store":"하남","item":"버터 사블레","qty":21,"net":58800,"cat_big":"베이커리","cat_mid":"구움과자","cat_small":"사블레"},{"store":"광주","item":"에스프레소(DARK)","qty":4,"net":21600,"cat_big":"음료","cat_mid":"공통","cat_small":"커피"},{"store":"가산","item":"홈 브루잉키트","qty":4,"net":160000,"cat_big":"MD/기타","cat_mid":"MD","cat_small":"기타"},{"store":"다산","item":"차가운우유","qty":6,"net":25800,"cat_big":"음료","cat_mid":"스페셜","cat_small":"키즈"},{"store":"다산","item":"에티오피아 커피백(페도라형)","qty":36,"net":72000,"cat_big":"MD/기타","cat_mid":"MD","cat_small":"커피류"},{"store":"다산","item":"에스프레소(R)","qty":14,"net":95200,"cat_big":"음료","cat_mid":"공통","cat_small":"커피"},{"store":"다산","item":"썸머 시트러스(조각)","qty":89,"net":845500,"cat_big":"베이커리","cat_mid":"케이크","cat_small":"조각 케이크"},{"store":"다산","item":"썸머 시트러스(1호)","qty":15,"net":630000,"cat_big":"베이커리","cat_mid":"케이크","cat_small":"홀 케이크"},{"store":"수원","item":"콜롬비아 디카페인(200g)","qty":7,"net":126000,"cat_big":"MD/기타","cat_mid":"MD","cat_small":"커피류"},{"store":"수원","item":"과테말라 럼배럴 에이지드 200g","qty":9,"net":297000,"cat_big":"MD/기타","cat_mid":"MD","cat_small":"커피류"},{"store":"수원","item":"콜롬비아 커피백(페도라형)","qty":33,"net":66000,"cat_big":"MD/기타","cat_mid":"MD","cat_small":"커피류"},{"store":"수원","item":"에티오피아 커피백(페도라형)","qty":28,"net":56000,"cat_big":"MD/기타","cat_mid":"MD","cat_small":"커피류"},{"store":"하남","item":"ETH 예가체프 코케허니G1(N)200g","qty":9,"net":166500,"cat_big":"MD/기타","cat_mid":"MD","cat_small":"커피류"},{"store":"하남","item":"H 엘살바도르 파카마라 내추럴","qty":7,"net":45500,"cat_big":"음료","cat_mid":"공통","cat_small":"드립커피"},{"store":"하남","item":"카페 모카","qty":11,"net":71500,"cat_big":"음료","cat_mid":"공통","cat_small":"커피"},{"store":"하남","item":"레몬 에이드","qty":23,"net":172500,"cat_big":"음료","cat_mid":"공통","cat_small":"에이드"},{"store":"하남","item":"초코 라떼","qty":21,"net":142800,"cat_big":"음료","cat_mid":"공통","cat_small":"논커피"},{"store":"광주","item":"하랑이 페이스쿠션","qty":7,"net":231000,"cat_big":"MD/기타","cat_mid":"MD","cat_small":"KIA Tigers"},{"store":"가산","item":"기프트카드1","qty":4,"net":40000,"cat_big":"MD/기타","cat_mid":"기타","cat_small":"기프트카드"},{"store":"가산","item":"버터 딸기잼","qty":4,"net":8000,"cat_big":"베이커리","cat_mid":"스프레드/잼/오일","cat_small":"잼"},{"store":"다산","item":"바닐라시럽","qty":6,"net":6000,"cat_big":"음료","cat_mid":"공통","cat_small":"커피"},{"store":"다산","item":"따뜻한우유","qty":10,"net":43000,"cat_big":"음료","cat_mid":"스페셜","cat_small":"키즈"},{"store":"다산","item":"드립백(에디오피아)","qty":2,"net":24000,"cat_big":"MD/기타","cat_mid":"MD","cat_small":"커피류"},{"store":"다산","item":"콜롬비아 커피백(페도라형)","qty":80,"net":160000,"cat_big":"MD/기타","cat_mid":"MD","cat_small":"커피류"},{"store":"다산","item":"인크 프렌치바닐라라떼(10입)","qty":4,"net":36000,"cat_big":"MD/기타","cat_mid":"MD","cat_small":"커피류"},{"store":"다산","item":"바이트 박스","qty":19,"net":19000,"cat_big":"MD/기타","cat_mid":"MD","cat_small":"포장"},{"store":"다산","item":"멀티기프트박스","qty":2,"net":6000,"cat_big":"MD/기타","cat_mid":"MD","cat_small":"포장"},{"store":"다산","item":"드립백(베이직)","qty":2,"net":22000,"cat_big":"MD/기타","cat_mid":"MD","cat_small":"커피류"},{"store":"수원","item":"그라운드 에티오피아(15T)","qty":1,"net":25000,"cat_big":"MD/기타","cat_mid":"MD","cat_small":"커피류"},{"store":"수원","item":"인크 오리진블렌드 200g","qty":10,"net":160000,"cat_big":"MD/기타","cat_mid":"MD","cat_small":"커피류"},{"store":"수원","item":"오렌지쇼핑백","qty":2,"net":1000,"cat_big":"MD/기타","cat_mid":"MD","cat_small":"포장"},{"store":"하남","item":"에티오피아 커피백(페도라형)","qty":6,"net":12000,"cat_big":"MD/기타","cat_mid":"MD","cat_small":"커피류"},{"store":"하남","item":"과테말라 럼배럴","qty":7,"net":56000,"cat_big":"음료","cat_mid":"공통","cat_small":"드립커피"},{"store":"하남","item":"에스프레소(DARK)","qty":3,"net":16200,"cat_big":"음료","cat_mid":"공통","cat_small":"커피"},{"store":"하남","item":"I 카페 모카","qty":10,"net":65000,"cat_big":"음료","cat_mid":"공통","cat_small":"커피"},{"store":"광주","item":"에스프레소(D)","qty":1,"net":5400,"cat_big":"음료","cat_mid":"공통","cat_small":"커피"},{"store":"광주","item":"에스프레소(R)","qty":4,"net":27200,"cat_big":"음료","cat_mid":"공통","cat_small":"커피"},{"store":"가산","item":"인크 글라스 서버+필터","qty":1,"net":14000,"cat_big":"MD/기타","cat_mid":"MD","cat_small":"기타"},{"store":"다산","item":"홈 브루잉키트","qty":1,"net":40000,"cat_big":"MD/기타","cat_mid":"MD","cat_small":"기타"},{"store":"하남","item":"얼그레이","qty":5,"net":29000,"cat_big":"음료","cat_mid":"공통","cat_small":"차"},{"store":"광주","item":"캠프컵 블랙 12oz","qty":2,"net":67000,"cat_big":"MD/기타","cat_mid":"MD","cat_small":"텀블러"},{"store":"광주","item":"인크 글라스 서버+필터","qty":3,"net":42000,"cat_big":"MD/기타","cat_mid":"MD","cat_small":"기타"},{"store":"광주","item":"에스프레소(INC)","qty":10,"net":54000,"cat_big":"음료","cat_mid":"공통","cat_small":"커피"},{"store":"가산","item":"그라운드 타이거즈(15T)","qty":2,"net":50000,"cat_big":"MD/기타","cat_mid":"MD","cat_small":"커피류"},{"store":"가산","item":"에스프레소샷잔","qty":1,"net":6000,"cat_big":"MD/기타","cat_mid":"MD","cat_small":"기타"},{"store":"가산","item":"리유저블백(M)","qty":5,"net":15000,"cat_big":"MD/기타","cat_mid":"MD","cat_small":"기타"},{"store":"가산","item":"인크 리유저블텀블러","qty":1,"net":7000,"cat_big":"MD/기타","cat_mid":"MD","cat_small":"기타"},{"store":"다산","item":"바질 치즈 스콘","qty":4,"net":19200,"cat_big":"베이커리","cat_mid":"구움과자","cat_small":"스콘"},{"store":"수원","item":"SLV 말라카라C파카마라N 200g","qty":7,"net":126000,"cat_big":"MD/기타","cat_mid":"MD","cat_small":"커피류"},{"store":"하남","item":"콜롬비아 커피백(페도라형)","qty":12,"net":24000,"cat_big":"MD/기타","cat_mid":"MD","cat_small":"커피류"},{"store":"가산","item":"그라운드 에티오피아(15T)","qty":1,"net":25000,"cat_big":"MD/기타","cat_mid":"MD","cat_small":"커피류"},{"store":"가산","item":"COL 캄포 에르모소(VH) 20g(after)","qty":4,"net":8000,"cat_big":"MD/기타","cat_mid":"MD","cat_small":"커피류"},{"store":"다산","item":"인크 스퀘어 글라스 머그 INC","qty":3,"net":33000,"cat_big":"MD/기타","cat_mid":"MD","cat_small":"테이블웨어"},{"store":"다산","item":"인크 스퀘어 글라스 머그 TTO","qty":2,"net":22000,"cat_big":"MD/기타","cat_mid":"MD","cat_small":"테이블웨어"},{"store":"다산","item":"에스프레소샷잔","qty":2,"net":12000,"cat_big":"MD/기타","cat_mid":"MD","cat_small":"기타"},{"store":"다산","item":"쇼핑백(흰) 대","qty":3,"net":3000,"cat_big":"MD/기타","cat_mid":"MD","cat_small":"포장"},{"store":"가산","item":"기프트카드2","qty":5,"net":150000,"cat_big":"MD/기타","cat_mid":"기타","cat_small":"기프트카드"},{"store":"다산","item":"그라운드 타이거즈(15T)","qty":2,"net":50000,"cat_big":"MD/기타","cat_mid":"MD","cat_small":"커피류"},{"store":"다산","item":"헤이즐넛 오렌지 휘낭시에","qty":3,"net":10500,"cat_big":"베이커리","cat_mid":"구움과자","cat_small":"휘낭시에"},{"store":"다산","item":"마시멜로 추가","qty":3,"net":1500,"cat_big":"음료","cat_mid":"스페셜","cat_small":"키즈"},{"store":"하남","item":"홈 브루잉키트","qty":1,"net":40000,"cat_big":"MD/기타","cat_mid":"MD","cat_small":"기타"},{"store":"광주","item":"소금빵 시나몬 러스크","qty":51,"net":265200,"cat_big":"베이커리","cat_mid":"브레드","cat_small":"일반빵"},{"store":"광주","item":"소금빵 러스크","qty":59,"net":306800,"cat_big":"베이커리","cat_mid":"브레드","cat_small":"일반빵"},{"store":"가산","item":"기프트카드4","qty":3,"net":300000,"cat_big":"MD/기타","cat_mid":"기타","cat_small":"기프트카드"},{"store":"하남","item":"콜롬비아 디카페인(200g)","qty":3,"net":54000,"cat_big":"MD/기타","cat_mid":"MD","cat_small":"커피류"},{"store":"광주","item":"H 엘살바도르 파카마라 내추럴(SP)","qty":1,"net":8000,"cat_big":"음료","cat_mid":"공통","cat_small":"싸이폰"},{"store":"광주","item":"H 에티오피아 코케허니(SP)","qty":1,"net":8000,"cat_big":"음료","cat_mid":"공통","cat_small":"싸이폰"},{"store":"다산","item":"인크 글라스 서버+필터","qty":1,"net":14000,"cat_big":"MD/기타","cat_mid":"MD","cat_small":"기타"},{"store":"다산","item":"리유저블백(M)","qty":3,"net":9000,"cat_big":"MD/기타","cat_mid":"MD","cat_small":"기타"},{"store":"하남","item":"I 겐마이차","qty":11,"net":63800,"cat_big":"음료","cat_mid":"공통","cat_small":"차"},{"store":"하남","item":"커피백 머그세트","qty":3,"net":96000,"cat_big":"MD/기타","cat_mid":"MD","cat_small":"선물세트"},{"store":"가산","item":"드립백(에디오피아)","qty":7,"net":84000,"cat_big":"MD/기타","cat_mid":"MD","cat_small":"커피류"},{"store":"수원","item":"인크 프렌치바닐라라떼(10입)","qty":1,"net":9000,"cat_big":"MD/기타","cat_mid":"MD","cat_small":"커피류"},{"store":"가산","item":"I 엘살바도르 파카마라 내추럴(SP)","qty":1,"net":8000,"cat_big":"음료","cat_mid":"공통","cat_small":"싸이폰"},{"store":"다산","item":"콜롬비아 디카페인(200g)","qty":5,"net":90000,"cat_big":"MD/기타","cat_mid":"MD","cat_small":"커피류"},{"store":"하남","item":"인크 클래식핫초코(10입)","qty":3,"net":27000,"cat_big":"MD/기타","cat_mid":"MD","cat_small":"커피류"},{"store":"가산","item":"인크이지보틀","qty":1,"net":5500,"cat_big":"MD/기타","cat_mid":"MD","cat_small":"텀블러"},{"store":"가산","item":"COL 산추아리오 골드워시드 20g","qty":3,"net":9000,"cat_big":"MD/기타","cat_mid":"MD","cat_small":"커피류"},{"store":"수원","item":"COL 캄포 에르모소(VH) 20g(after)","qty":1,"net":2000,"cat_big":"MD/기타","cat_mid":"MD","cat_small":"커피류"},{"store":"광주","item":"VIP 전용","qty":1,"net":468400,"cat_big":"MD/기타","cat_mid":"기타","cat_small":"특판"},{"store":"가산","item":"멀티기프트박스","qty":1,"net":3000,"cat_big":"MD/기타","cat_mid":"MD","cat_small":"포장"},{"store":"수원","item":"과테말라 럼배럴 커피파우더","qty":1,"net":14000,"cat_big":"MD/기타","cat_mid":"MD","cat_small":"커피류"},{"store":"수원","item":"COL 산추아리오 골드워시드 20g(after)","qty":1,"net":2000,"cat_big":"MD/기타","cat_mid":"MD","cat_small":"커피류"},{"store":"광주","item":"바이트 박스","qty":8,"net":8000,"cat_big":"MD/기타","cat_mid":"MD","cat_small":"포장"},{"store":"가산","item":"인크 스퀘어 글라스 머그 TTO","qty":1,"net":11000,"cat_big":"MD/기타","cat_mid":"MD","cat_small":"테이블웨어"},{"store":"다산","item":"소금빵 시나몬 러스크","qty":4,"net":20800,"cat_big":"베이커리","cat_mid":"브레드","cat_small":"일반빵"},{"store":"다산","item":"몬스터 얼그레이 휘낭시에","qty":22,"net":88000,"cat_big":"베이커리","cat_mid":"구움과자","cat_small":"휘낭시에"},{"store":"다산","item":"잭 오랜턴 황치즈 휘낭시에","qty":21,"net":84000,"cat_big":"베이커리","cat_mid":"구움과자","cat_small":"휘낭시에"},{"store":"다산","item":"할로윈 6입 set","qty":16,"net":320000,"cat_big":"베이커리","cat_mid":"구움과자","cat_small":"빼빼로"},{"store":"광주","item":"미라 더블 초콜릿 쿠키","qty":19,"net":79800,"cat_big":"베이커리","cat_mid":"구움과자","cat_small":"쿠키"},{"store":"광주","item":"고스트 크렌베리 아몬드 쿠키","qty":18,"net":68400,"cat_big":"베이커리","cat_mid":"구움과자","cat_small":"쿠키"},{"store":"광주","item":"잭 오랜턴 황치즈 휘낭시에","qty":11,"net":44000,"cat_big":"베이커리","cat_mid":"구움과자","cat_small":"휘낭시에"},{"store":"광주","item":"할로윈 6입 set","qty":7,"net":140000,"cat_big":"베이커리","cat_mid":"구움과자","cat_small":"빼빼로"},{"store":"가산","item":"RIP 레몬 마들렌","qty":11,"net":44000,"cat_big":"베이커리","cat_mid":"구움과자","cat_small":"마들렌"},{"store":"가산","item":"미라 초콜릿 마들렌","qty":23,"net":92000,"cat_big":"베이커리","cat_mid":"구움과자","cat_small":"마들렌"},{"store":"가산","item":"몬스터 얼그레이 휘낭시에","qty":29,"net":116000,"cat_big":"베이커리","cat_mid":"구움과자","cat_small":"휘낭시에"},{"store":"가산","item":"잭 오랜턴 황치즈 휘낭시에","qty":25,"net":100000,"cat_big":"베이커리","cat_mid":"구움과자","cat_small":"휘낭시에"},{"store":"가산","item":"할로윈 6입 set","qty":19,"net":380000,"cat_big":"베이커리","cat_mid":"구움과자","cat_small":"빼빼로"},{"store":"다산","item":"RIP 레몬 마들렌","qty":8,"net":32000,"cat_big":"베이커리","cat_mid":"구움과자","cat_small":"마들렌"},{"store":"다산","item":"미라 초콜릿 마들렌","qty":21,"net":84000,"cat_big":"베이커리","cat_mid":"구움과자","cat_small":"마들렌"},{"store":"다산","item":"미라 더블 초콜릿 쿠키","qty":22,"net":92400,"cat_big":"베이커리","cat_mid":"구움과자","cat_small":"쿠키"},{"store":"다산","item":"고스트 크렌베리 아몬드 쿠키","qty":14,"net":53200,"cat_big":"베이커리","cat_mid":"구움과자","cat_small":"쿠키"},{"store":"수원","item":"십원(수원점)","qty":2,"net":20,"cat_big":"음료","cat_mid":"음료","cat_small":"스타필드 수원점"},{"store":"수원","item":"RIP 레몬 마들렌","qty":17,"net":68000,"cat_big":"베이커리","cat_mid":"구움과자","cat_small":"마들렌"},{"store":"수원","item":"미라 초콜릿 마들렌","qty":25,"net":100000,"cat_big":"베이커리","cat_mid":"구움과자","cat_small":"마들렌"},{"store":"수원","item":"미라 더블 초콜릿 쿠키","qty":26,"net":109200,"cat_big":"베이커리","cat_mid":"구움과자","cat_small":"쿠키"},{"store":"수원","item":"고스트 크렌베리 아몬드 쿠키","qty":23,"net":87400,"cat_big":"베이커리","cat_mid":"구움과자","cat_small":"쿠키"},{"store":"수원","item":"몬스터 얼그레이 휘낭시에","qty":22,"net":88000,"cat_big":"베이커리","cat_mid":"구움과자","cat_small":"휘낭시에"},{"store":"수원","item":"잭 오랜턴 황치즈 휘낭시에","qty":29,"net":116000,"cat_big":"베이커리","cat_mid":"구움과자","cat_small":"휘낭시에"},{"store":"광주","item":"RIP 레몬 마들렌","qty":6,"net":24000,"cat_big":"베이커리","cat_mid":"구움과자","cat_small":"마들렌"},{"store":"광주","item":"미라 초콜릿 마들렌","qty":16,"net":64000,"cat_big":"베이커리","cat_mid":"구움과자","cat_small":"마들렌"},{"store":"광주","item":"몬스터 얼그레이 휘낭시에","qty":11,"net":44000,"cat_big":"베이커리","cat_mid":"구움과자","cat_small":"휘낭시에"},{"store":"가산","item":"기프트카드3","qty":1,"net":50000,"cat_big":"MD/기타","cat_mid":"기타","cat_small":"기프트카드"},{"store":"가산","item":"미라 더블 초콜릿 쿠키","qty":23,"net":96600,"cat_big":"베이커리","cat_mid":"구움과자","cat_small":"쿠키"},{"store":"다산","item":"코코넛 마들렌","qty":1,"net":3500,"cat_big":"베이커리","cat_mid":"구움과자","cat_small":"마들렌"},{"store":"하남","item":"론자카파 럼배럴 에이지드 200g","qty":1,"net":33000,"cat_big":"MD/기타","cat_mid":"MD","cat_small":"커피류"},{"store":"가산","item":"H 엘살바도르 파카마라 내추럴(SP)","qty":2,"net":16000,"cat_big":"음료","cat_mid":"공통","cat_small":"싸이폰"},{"store":"수원","item":"캡슐 인크오리진(10pcs)","qty":3,"net":27000,"cat_big":"MD/기타","cat_mid":"MD","cat_small":"커피류"},{"store":"수원","item":"인크 리유저블텀블러","qty":2,"net":14000,"cat_big":"MD/기타","cat_mid":"MD","cat_small":"기타"},{"store":"수원","item":"바이트 박스","qty":1,"net":1000,"cat_big":"MD/기타","cat_mid":"MD","cat_small":"포장"},{"store":"수원","item":"에스프레소(D)","qty":1,"net":5400,"cat_big":"음료","cat_mid":"공통","cat_small":"커피"},{"store":"수원","item":"할로윈 6입 set","qty":1,"net":20000,"cat_big":"베이커리","cat_mid":"구움과자","cat_small":"빼빼로"},{"store":"가산","item":"캡슐 인크오리진(10pcs)","qty":1,"net":9000,"cat_big":"MD/기타","cat_mid":"MD","cat_small":"커피류"},{"store":"가산","item":"고스트 크렌베리 아몬드 쿠키","qty":11,"net":41800,"cat_big":"베이커리","cat_mid":"구움과자","cat_small":"쿠키"},{"store":"광주","item":"홈 브루잉키트","qty":1,"net":40000,"cat_big":"MD/기타","cat_mid":"MD","cat_small":"기타"},{"store":"다산","item":"NEW GIFT BOX A","qty":30,"net":6000000,"cat_big":"MD/기타","cat_mid":"MD","cat_small":"선물세트"},{"store":"다산","item":"옥수수 베이글","qty":2,"net":11000,"cat_big":"베이커리","cat_mid":"브레드","cat_small":"베이글"},{"store":"다산","item":"피스타치오 퀸 아망","qty":1,"net":6000,"cat_big":"베이커리","cat_mid":"페이스트리","cat_small":"퀸 아망"},{"store":"수원","item":"캠프컵 블랙 12oz","qty":1,"net":33500,"cat_big":"MD/기타","cat_mid":"MD","cat_small":"텀블러"},{"store":"하남","item":"리유저블마켓백","qty":1,"net":12000,"cat_big":"MD/기타","cat_mid":"MD","cat_small":"기타"},{"store":"광주","item":"캡슐 인크오리진(10pcs)","qty":3,"net":27000,"cat_big":"MD/기타","cat_mid":"MD","cat_small":"커피류"}]}